{
"meta":{"test_sets":[],"test_metrics":[],"learn_metrics":[{"best_value":"Min","name":"Logloss"}],"launch_mode":"Train","parameters":"","iteration_count":1000,"learn_sets":["learn"],"name":"experiment"},
"iterations":[
{"learn":[0.6753405447],"iteration":0,"passed_time":0.01058672373,"remaining_time":10.57613701},
{"learn":[0.6600300056],"iteration":1,"passed_time":0.01952242606,"remaining_time":9.741690602},
{"learn":[0.6406708722],"iteration":2,"passed_time":0.0275622822,"remaining_time":9.159865118},
{"learn":[0.6213756276],"iteration":3,"passed_time":0.03583334372,"remaining_time":8.922502587},
{"learn":[0.6069068882],"iteration":4,"passed_time":0.04408356431,"remaining_time":8.772629297},
{"learn":[0.5908379458],"iteration":5,"passed_time":0.05248480817,"remaining_time":8.69498322},
{"learn":[0.5750718792],"iteration":6,"passed_time":0.06088626317,"remaining_time":8.637151333},
{"learn":[0.5624038686],"iteration":7,"passed_time":0.06918419717,"remaining_time":8.578840449},
{"learn":[0.5509290462],"iteration":8,"passed_time":0.08028680849,"remaining_time":8.84046969},
{"learn":[0.5376406747],"iteration":9,"passed_time":0.08855141731,"remaining_time":8.766590314},
{"learn":[0.5270962872],"iteration":10,"passed_time":0.09670759932,"remaining_time":8.694892339},
{"learn":[0.5147629263],"iteration":11,"passed_time":0.1046181639,"remaining_time":8.613562159},
{"learn":[0.505176829],"iteration":12,"passed_time":0.1126533026,"remaining_time":8.552985362},
{"learn":[0.4934227272],"iteration":13,"passed_time":0.1209756573,"remaining_time":8.520142722},
{"learn":[0.4822578084],"iteration":14,"passed_time":0.1290551964,"remaining_time":8.474624562},
{"learn":[0.4726945833],"iteration":15,"passed_time":0.1373331247,"remaining_time":8.445987169},
{"learn":[0.4650730258],"iteration":16,"passed_time":0.1464416777,"remaining_time":8.467774657},
{"learn":[0.4585142808],"iteration":17,"passed_time":0.1555869583,"remaining_time":8.48813295},
{"learn":[0.4493867777],"iteration":18,"passed_time":0.1634584574,"remaining_time":8.439618248},
{"learn":[0.4427761975],"iteration":19,"passed_time":0.172096094,"remaining_time":8.432708605},
{"learn":[0.4361403599],"iteration":20,"passed_time":0.1812048209,"remaining_time":8.447596173},
{"learn":[0.4292194076],"iteration":21,"passed_time":0.1905279563,"remaining_time":8.469833694},
{"learn":[0.4244214395],"iteration":22,"passed_time":0.1995670568,"remaining_time":8.477261498},
{"learn":[0.4191859605],"iteration":23,"passed_time":0.207362,"remaining_time":8.432721334},
{"learn":[0.4139331464],"iteration":24,"passed_time":0.2164295045,"remaining_time":8.440750677},
{"learn":[0.409373143],"iteration":25,"passed_time":0.2238577379,"remaining_time":8.38605526},
{"learn":[0.403151007],"iteration":26,"passed_time":0.2322994691,"remaining_time":8.37138457},
{"learn":[0.3982252186],"iteration":27,"passed_time":0.2405050022,"remaining_time":8.348959364},
{"learn":[0.3931258655],"iteration":28,"passed_time":0.2482485995,"remaining_time":8.312047933},
{"learn":[0.389041323],"iteration":29,"passed_time":0.2566875649,"remaining_time":8.299564598},
{"learn":[0.3838685402],"iteration":30,"passed_time":0.2658778189,"remaining_time":8.310826017},
{"learn":[0.3803423864],"iteration":31,"passed_time":0.2739548902,"remaining_time":8.287135428},
{"learn":[0.3761229106],"iteration":32,"passed_time":0.2821891775,"remaining_time":8.26899802},
{"learn":[0.3730630176],"iteration":33,"passed_time":0.2909024754,"remaining_time":8.265052684},
{"learn":[0.3694191804],"iteration":34,"passed_time":0.299397244,"remaining_time":8.254809726},
{"learn":[0.364344531],"iteration":35,"passed_time":0.3077417258,"remaining_time":8.240639546},
{"learn":[0.3607035475],"iteration":36,"passed_time":0.3170990574,"remaining_time":8.253145738},
{"learn":[0.3573742565],"iteration":37,"passed_time":0.3247003761,"remaining_time":8.220046363},
{"learn":[0.3546728652],"iteration":38,"passed_time":0.3329741884,"remaining_time":8.204825515},
{"learn":[0.352105172],"iteration":39,"passed_time":0.3413018787,"remaining_time":8.191245088},
{"learn":[0.3477804286],"iteration":40,"passed_time":0.3498155108,"remaining_time":8.182270118},
{"learn":[0.345380614],"iteration":41,"passed_time":0.3591890248,"remaining_time":8.192930613},
{"learn":[0.3433962048],"iteration":42,"passed_time":0.3694691939,"remaining_time":8.22283764},
{"learn":[0.3413170058],"iteration":43,"passed_time":0.377997454,"remaining_time":8.212853774},
{"learn":[0.3387740162],"iteration":44,"passed_time":0.3868356297,"remaining_time":8.209511696},
{"learn":[0.3359862046],"iteration":45,"passed_time":0.3960398329,"remaining_time":8.213521752},
{"learn":[0.3339610343],"iteration":46,"passed_time":0.4044908659,"remaining_time":8.20169777},
{"learn":[0.3307337099],"iteration":47,"passed_time":0.4126871229,"remaining_time":8.184961271},
{"learn":[0.3288035423],"iteration":48,"passed_time":0.4208807088,"remaining_time":8.168521512},
{"learn":[0.3262306102],"iteration":49,"passed_time":0.4286158883,"remaining_time":8.143701877},
{"learn":[0.3244643601],"iteration":50,"passed_time":0.4368347789,"remaining_time":8.128553043},
{"learn":[0.3219911159],"iteration":51,"passed_time":0.4453929115,"remaining_time":8.119855387},
{"learn":[0.3197432503],"iteration":52,"passed_time":0.4535423753,"remaining_time":8.103860932},
{"learn":[0.3183257695],"iteration":53,"passed_time":0.4615438668,"remaining_time":8.085564777},
{"learn":[0.3169179572],"iteration":54,"passed_time":0.4703706924,"remaining_time":8.081823716},
{"learn":[0.3149897062],"iteration":55,"passed_time":0.4785946159,"remaining_time":8.067737811},
{"learn":[0.3136695069],"iteration":56,"passed_time":0.4869238262,"remaining_time":8.05559944},
{"learn":[0.3117225578],"iteration":57,"passed_time":0.4959673528,"remaining_time":8.055193903},
{"learn":[0.3095198403],"iteration":58,"passed_time":0.5043063524,"remaining_time":8.043258942},
{"learn":[0.3075943579],"iteration":59,"passed_time":0.5131964442,"remaining_time":8.040077625},
{"learn":[0.3056552884],"iteration":60,"passed_time":0.5209940474,"remaining_time":8.019891975},
{"learn":[0.303582244],"iteration":61,"passed_time":0.529703153,"remaining_time":8.013896088},
{"learn":[0.3020579624],"iteration":62,"passed_time":0.5379175958,"remaining_time":8.000456941},
{"learn":[0.3009364786],"iteration":63,"passed_time":0.5469571059,"remaining_time":7.999247674},
{"learn":[0.2994267423],"iteration":64,"passed_time":0.5568643761,"remaining_time":8.010279871},
{"learn":[0.2978873829],"iteration":65,"passed_time":0.5658375181,"remaining_time":8.00745821},
{"learn":[0.2965249104],"iteration":66,"passed_time":0.574040913,"remaining_time":7.993733908},
{"learn":[0.2949686842],"iteration":67,"passed_time":0.58193352,"remaining_time":7.975912362},
{"learn":[0.2933529776],"iteration":68,"passed_time":0.5903181569,"remaining_time":7.965017451},
{"learn":[0.2923179781],"iteration":69,"passed_time":0.5995245889,"remaining_time":7.965112396},
{"learn":[0.2905100938],"iteration":70,"passed_time":0.608077472,"remaining_time":7.956393964},
{"learn":[0.2892057388],"iteration":71,"passed_time":0.6160362851,"remaining_time":7.94002323},
{"learn":[0.2880148505],"iteration":72,"passed_time":0.6245057634,"remaining_time":7.930367708},
{"learn":[0.2868352918],"iteration":73,"passed_time":0.632606381,"remaining_time":7.916128497},
{"learn":[0.2860530579],"iteration":74,"passed_time":0.6407812642,"remaining_time":7.902968925},
{"learn":[0.2840445839],"iteration":75,"passed_time":0.6493522832,"remaining_time":7.894756706},
{"learn":[0.2824606087],"iteration":76,"passed_time":0.6579077305,"remaining_time":7.88634851},
{"learn":[0.2818538349],"iteration":77,"passed_time":0.6665556662,"remaining_time":7.879029797},
{"learn":[0.2807245354],"iteration":78,"passed_time":0.690171931,"remaining_time":8.046181626},
{"learn":[0.2794357481],"iteration":79,"passed_time":0.6991843217,"remaining_time":8.0406197},
{"learn":[0.2787502206],"iteration":80,"passed_time":0.708403594,"remaining_time":8.037319788},
{"learn":[0.2779238182],"iteration":81,"passed_time":0.7165302313,"remaining_time":8.021643321},
{"learn":[0.2767752243],"iteration":82,"passed_time":0.7250202113,"remaining_time":8.010163057},
{"learn":[0.2761414043],"iteration":83,"passed_time":0.7336490555,"remaining_time":8.000268271},
{"learn":[0.2754059796],"iteration":84,"passed_time":0.7420746764,"remaining_time":7.988215635},
{"learn":[0.2746833327],"iteration":85,"passed_time":0.7512833785,"remaining_time":7.98456986},
{"learn":[0.2729792465],"iteration":86,"passed_time":0.7592157298,"remaining_time":7.967401855},
{"learn":[0.2723578209],"iteration":87,"passed_time":0.7682539246,"remaining_time":7.96190431},
{"learn":[0.2717784341],"iteration":88,"passed_time":0.7764679992,"remaining_time":7.947891543},
{"learn":[0.2707059744],"iteration":89,"passed_time":0.7852693772,"remaining_time":7.939945925},
{"learn":[0.2700339488],"iteration":90,"passed_time":0.7937395463,"remaining_time":7.92867305},
{"learn":[0.2694941945],"iteration":91,"passed_time":0.802424887,"remaining_time":7.919584754},
{"learn":[0.2690254845],"iteration":92,"passed_time":0.811999963,"remaining_time":7.919182435},
{"learn":[0.2684866246],"iteration":93,"passed_time":0.8202702008,"remaining_time":7.906008531},
{"learn":[0.267763786],"iteration":94,"passed_time":0.8284062874,"remaining_time":7.891659895},
{"learn":[0.26677583],"iteration":95,"passed_time":0.8359357702,"remaining_time":7.871728503},
{"learn":[0.2661349609],"iteration":96,"passed_time":0.8452087252,"remaining_time":7.868283287},
{"learn":[0.2651711974],"iteration":97,"passed_time":0.8531069064,"remaining_time":7.852065608},
{"learn":[0.2643789117],"iteration":98,"passed_time":0.8621744743,"remaining_time":7.846658599},
{"learn":[0.2637979916],"iteration":99,"passed_time":0.8699569523,"remaining_time":7.82961257},
{"learn":[0.2632993604],"iteration":100,"passed_time":0.8784188153,"remaining_time":7.818797178},
{"learn":[0.2625930477],"iteration":101,"passed_time":0.8863126747,"remaining_time":7.803027273},
{"learn":[0.2615454621],"iteration":102,"passed_time":0.8942197756,"remaining_time":7.787525619},
{"learn":[0.2609871374],"iteration":103,"passed_time":0.9027926219,"remaining_time":7.777905666},
{"learn":[0.260356171],"iteration":104,"passed_time":0.9115757556,"remaining_time":7.770098107},
{"learn":[0.259779638],"iteration":105,"passed_time":0.9202179241,"remaining_time":7.761083247},
{"learn":[0.2591916901],"iteration":106,"passed_time":0.9296755198,"remaining_time":7.75888074},
{"learn":[0.2587737505],"iteration":107,"passed_time":0.9387756901,"remaining_time":7.75359181},
{"learn":[0.2580863915],"iteration":108,"passed_time":0.9487170633,"remaining_time":7.755109206},
{"learn":[0.2575736409],"iteration":109,"passed_time":0.9580508155,"remaining_time":7.751502053},
{"learn":[0.2571181559],"iteration":110,"passed_time":0.9670161381,"remaining_time":7.744840962},
{"learn":[0.2562900711],"iteration":111,"passed_time":0.9753423328,"remaining_time":7.733071353},
{"learn":[0.2557933991],"iteration":112,"passed_time":0.9867412962,"remaining_time":7.745482564},
{"learn":[0.2552072827],"iteration":113,"passed_time":0.9950608885,"remaining_time":7.733543397},
{"learn":[0.2549208903],"iteration":114,"passed_time":1.003817345,"remaining_time":7.725029135},
{"learn":[0.2545169423],"iteration":115,"passed_time":1.012312036,"remaining_time":7.714515863},
{"learn":[0.2540387555],"iteration":116,"passed_time":1.021069881,"remaining_time":7.706023118},
{"learn":[0.2534013364],"iteration":117,"passed_time":1.029275862,"remaining_time":7.693400937},
{"learn":[0.2528327468],"iteration":118,"passed_time":1.037639436,"remaining_time":7.68201969},
{"learn":[0.252282536],"iteration":119,"passed_time":1.04602577,"remaining_time":7.670855646},
{"learn":[0.2519069547],"iteration":120,"passed_time":1.055315643,"remaining_time":7.666301242},
{"learn":[0.2514307271],"iteration":121,"passed_time":1.06521279,"remaining_time":7.666039585},
{"learn":[0.2510774004],"iteration":122,"passed_time":1.073435457,"remaining_time":7.653682077},
{"learn":[0.250891782],"iteration":123,"passed_time":1.081938907,"remaining_time":7.643374859},
{"learn":[0.2502929517],"iteration":124,"passed_time":1.091206224,"remaining_time":7.638443571},
{"learn":[0.249301354],"iteration":125,"passed_time":1.100070878,"remaining_time":7.630650377},
{"learn":[0.2488210802],"iteration":126,"passed_time":1.108452149,"remaining_time":7.619517526},
{"learn":[0.248313398],"iteration":127,"passed_time":1.117863821,"remaining_time":7.615447281},
{"learn":[0.2478794436],"iteration":128,"passed_time":1.126459657,"remaining_time":7.605785744},
{"learn":[0.2474548382],"iteration":129,"passed_time":1.134955457,"remaining_time":7.595471138},
{"learn":[0.2471640588],"iteration":130,"passed_time":1.14420966,"remaining_time":7.590215224},
{"learn":[0.2468655487],"iteration":131,"passed_time":1.152657059,"remaining_time":7.579593386},
{"learn":[0.2465873979],"iteration":132,"passed_time":1.161406312,"remaining_time":7.570971973},
{"learn":[0.2462427814],"iteration":133,"passed_time":1.169252734,"remaining_time":7.556513936},
{"learn":[0.2460086074],"iteration":134,"passed_time":1.177762352,"remaining_time":7.546403216},
{"learn":[0.2457219594],"iteration":135,"passed_time":1.185251849,"remaining_time":7.529835274},
{"learn":[0.2453655661],"iteration":136,"passed_time":1.193696819,"remaining_time":7.519418647},
{"learn":[0.244897133],"iteration":137,"passed_time":1.201853462,"remaining_time":7.507229593},
{"learn":[0.2443988851],"iteration":138,"passed_time":1.209620663,"remaining_time":7.492686266},
{"learn":[0.2441639231],"iteration":139,"passed_time":1.216967908,"remaining_time":7.475660008},
{"learn":[0.2436263623],"iteration":140,"passed_time":1.225886493,"remaining_time":7.468343952},
{"learn":[0.2433384578],"iteration":141,"passed_time":1.234037405,"remaining_time":7.456366859},
{"learn":[0.2429611089],"iteration":142,"passed_time":1.241895348,"remaining_time":7.442687506},
{"learn":[0.2426698396],"iteration":143,"passed_time":1.249831921,"remaining_time":7.429556419},
{"learn":[0.2423778675],"iteration":144,"passed_time":1.258178009,"remaining_time":7.41891171},
{"learn":[0.2417421308],"iteration":145,"passed_time":1.265990561,"remaining_time":7.405177664},
{"learn":[0.2413853541],"iteration":146,"passed_time":1.2738332,"remaining_time":7.391698772},
{"learn":[0.2410239135],"iteration":147,"passed_time":1.285187858,"remaining_time":7.398513883},
{"learn":[0.2406850896],"iteration":148,"passed_time":1.29273668,"remaining_time":7.38334842},
{"learn":[0.2402985194],"iteration":149,"passed_time":1.300954982,"remaining_time":7.372078232},
{"learn":[0.2400745677],"iteration":150,"passed_time":1.308917094,"remaining_time":7.359408031},
{"learn":[0.2397040549],"iteration":151,"passed_time":1.31654612,"remaining_time":7.344941511},
{"learn":[0.239320168],"iteration":152,"passed_time":1.323671223,"remaining_time":7.327774679},
{"learn":[0.2390286219],"iteration":153,"passed_time":1.332439445,"remaining_time":7.319764743},
{"learn":[0.2387919988],"iteration":154,"passed_time":1.341037972,"remaining_time":7.310819914},
{"learn":[0.2384692536],"iteration":155,"passed_time":1.348738939,"remaining_time":7.297023488},
{"learn":[0.2380726742],"iteration":156,"passed_time":1.356526456,"remaining_time":7.28376944},
{"learn":[0.2376869984],"iteration":157,"passed_time":1.364267727,"remaining_time":7.27033814},
{"learn":[0.2374765059],"iteration":158,"passed_time":1.371879349,"remaining_time":7.256292658},
{"learn":[0.2371530366],"iteration":159,"passed_time":1.380688323,"remaining_time":7.248613696},
{"learn":[0.2368341886],"iteration":160,"passed_time":1.39231032,"remaining_time":7.255579869},
{"learn":[0.2365332082],"iteration":161,"passed_time":1.400462488,"remaining_time":7.244367686},
{"learn":[0.2362922195],"iteration":162,"passed_time":1.408981809,"remaining_time":7.23507837},
{"learn":[0.2359844668],"iteration":163,"passed_time":1.417717933,"remaining_time":7.226903611},
{"learn":[0.2357236512],"iteration":164,"passed_time":1.425865196,"remaining_time":7.215742052},
{"learn":[0.2351237348],"iteration":165,"passed_time":1.434434673,"remaining_time":7.206738057},
{"learn":[0.2349154997],"iteration":166,"passed_time":1.442315857,"remaining_time":7.194306039},
{"learn":[0.2345766758],"iteration":167,"passed_time":1.450373455,"remaining_time":7.18280187},
{"learn":[0.2343794296],"iteration":168,"passed_time":1.45847823,"remaining_time":7.171570466},
{"learn":[0.2340430548],"iteration":169,"passed_time":1.466980837,"remaining_time":7.162318205},
{"learn":[0.2334005245],"iteration":170,"passed_time":1.474966772,"remaining_time":7.150569907},
{"learn":[0.2331500376],"iteration":171,"passed_time":1.484554767,"remaining_time":7.146577599},
{"learn":[0.2328804692],"iteration":172,"passed_time":1.49325188,"remaining_time":7.138261875},
{"learn":[0.232469962],"iteration":173,"passed_time":1.501973058,"remaining_time":7.13005601},
{"learn":[0.23204459],"iteration":174,"passed_time":1.51141822,"remaining_time":7.125257321},
{"learn":[0.2318952178],"iteration":175,"passed_time":1.519707263,"remaining_time":7.114993095},
{"learn":[0.2315586087],"iteration":176,"passed_time":1.528364902,"remaining_time":7.10646505},
{"learn":[0.2312984107],"iteration":177,"passed_time":1.536997885,"remaining_time":7.097821696},
{"learn":[0.2307897702],"iteration":178,"passed_time":1.544962786,"remaining_time":7.086114232},
{"learn":[0.2305667555],"iteration":179,"passed_time":1.552800695,"remaining_time":7.073869833},
{"learn":[0.2302386862],"iteration":180,"passed_time":1.561143191,"remaining_time":7.06395731},
{"learn":[0.2300805187],"iteration":181,"passed_time":1.569181454,"remaining_time":7.052694669},
{"learn":[0.2298252401],"iteration":182,"passed_time":1.576617602,"remaining_time":7.038779129},
{"learn":[0.2295110986],"iteration":183,"passed_time":1.584633394,"remaining_time":7.027504615},
{"learn":[0.2288259971],"iteration":184,"passed_time":1.592702085,"remaining_time":7.016498375},
{"learn":[0.2285346426],"iteration":185,"passed_time":1.600946668,"remaining_time":7.006293483},
{"learn":[0.2281864696],"iteration":186,"passed_time":1.608792103,"remaining_time":6.994374222},
{"learn":[0.2278452392],"iteration":187,"passed_time":1.616376645,"remaining_time":6.981371467},
{"learn":[0.2276773606],"iteration":188,"passed_time":1.624566503,"remaining_time":6.971023459},
{"learn":[0.2275050097],"iteration":189,"passed_time":1.632460708,"remaining_time":6.959437753},
{"learn":[0.2273715033],"iteration":190,"passed_time":1.641142441,"remaining_time":6.951226361},
{"learn":[0.2271662071],"iteration":191,"passed_time":1.650283708,"remaining_time":6.944943938},
{"learn":[0.2269365267],"iteration":192,"passed_time":1.660193163,"remaining_time":6.941843949},
{"learn":[0.2267082731],"iteration":193,"passed_time":1.669957887,"remaining_time":6.938072459},
{"learn":[0.226442538],"iteration":194,"passed_time":1.677719227,"remaining_time":6.925969117},
{"learn":[0.2262218659],"iteration":195,"passed_time":1.685681277,"remaining_time":6.914733402},
{"learn":[0.2260168466],"iteration":196,"passed_time":1.693902284,"remaining_time":6.904586467},
{"learn":[0.2254816283],"iteration":197,"passed_time":1.701672151,"remaining_time":6.892631644},
{"learn":[0.2250873063],"iteration":198,"passed_time":1.70987862,"remaining_time":6.882476253},
{"learn":[0.224836223],"iteration":199,"passed_time":1.717240242,"remaining_time":6.868960967},
{"learn":[0.2247163249],"iteration":200,"passed_time":1.725326268,"remaining_time":6.858386509},
{"learn":[0.2244546149],"iteration":201,"passed_time":1.733273236,"remaining_time":6.84728734},
{"learn":[0.2242423974],"iteration":202,"passed_time":1.741876837,"remaining_time":6.838797237},
{"learn":[0.2240169549],"iteration":203,"passed_time":1.749932926,"remaining_time":6.828169653},
{"learn":[0.2237778828],"iteration":204,"passed_time":1.758388822,"remaining_time":6.819117627},
{"learn":[0.2235882181],"iteration":205,"passed_time":1.766696327,"remaining_time":6.809499434},
{"learn":[0.2233515524],"iteration":206,"passed_time":1.775544863,"remaining_time":6.801966554},
{"learn":[0.2229673461],"iteration":207,"passed_time":1.783340099,"remaining_time":6.790410375},
{"learn":[0.2225971315],"iteration":208,"passed_time":1.791949285,"remaining_time":6.781970738},
{"learn":[0.222355589],"iteration":209,"passed_time":1.80013806,"remaining_time":6.771947938},
{"learn":[0.2220969882],"iteration":210,"passed_time":1.808984493,"remaining_time":6.76440173},
{"learn":[0.2219709355],"iteration":211,"passed_time":1.817302282,"remaining_time":6.754878294},
{"learn":[0.2217674921],"iteration":212,"passed_time":1.825016371,"remaining_time":6.743135604},
{"learn":[0.2214554802],"iteration":213,"passed_time":1.83427803,"remaining_time":6.737114634},
{"learn":[0.2212226692],"iteration":214,"passed_time":1.842807886,"remaining_time":6.728391583},
{"learn":[0.2209529304],"iteration":215,"passed_time":1.851010384,"remaining_time":6.718482136},
{"learn":[0.2207569407],"iteration":216,"passed_time":1.858858328,"remaining_time":6.707309082},
{"learn":[0.2204006751],"iteration":217,"passed_time":1.8670133,"remaining_time":6.697267891},
{"learn":[0.2199769216],"iteration":218,"passed_time":1.87469022,"remaining_time":6.685539097},
{"learn":[0.2198544467],"iteration":219,"passed_time":1.882584431,"remaining_time":6.674617529},
{"learn":[0.2195870505],"iteration":220,"passed_time":1.890419269,"remaining_time":6.663514074},
{"learn":[0.219381946],"iteration":221,"passed_time":1.898405059,"remaining_time":6.652969081},
{"learn":[0.2192097442],"iteration":222,"passed_time":1.907008492,"remaining_time":6.644599095},
{"learn":[0.2189972712],"iteration":223,"passed_time":1.914760196,"remaining_time":6.633276394},
{"learn":[0.2187960639],"iteration":224,"passed_time":1.922550163,"remaining_time":6.622117228},
{"learn":[0.2186486723],"iteration":225,"passed_time":1.930575012,"remaining_time":6.611792297},
{"learn":[0.2180624281],"iteration":226,"passed_time":1.938805662,"remaining_time":6.602188444},
{"learn":[0.2178785986],"iteration":227,"passed_time":1.946703764,"remaining_time":6.591470641},
{"learn":[0.2177577208],"iteration":228,"passed_time":1.955154857,"remaining_time":6.582639277},
{"learn":[0.217501271],"iteration":229,"passed_time":1.963959829,"remaining_time":6.57499595},
{"learn":[0.2170247453],"iteration":230,"passed_time":1.972025412,"remaining_time":6.564881133},
{"learn":[0.2167535371],"iteration":231,"passed_time":1.979839773,"remaining_time":6.553952351},
{"learn":[0.2165779066],"iteration":232,"passed_time":1.988398219,"remaining_time":6.545499718},
{"learn":[0.2164303233],"iteration":233,"passed_time":1.996640111,"remaining_time":6.536009936},
{"learn":[0.2162359308],"iteration":234,"passed_time":2.005052955,"remaining_time":6.527087278},
{"learn":[0.2160590439],"iteration":235,"passed_time":2.012960536,"remaining_time":6.51653326},
{"learn":[0.2158902708],"iteration":236,"passed_time":2.020740574,"remaining_time":6.505590962},
{"learn":[0.21569492],"iteration":237,"passed_time":2.028851522,"remaining_time":6.495734705},
{"learn":[0.2154664534],"iteration":238,"passed_time":2.036894441,"remaining_time":6.485676442},
{"learn":[0.2151936054],"iteration":239,"passed_time":2.046353578,"remaining_time":6.480119662},
{"learn":[0.215111423],"iteration":240,"passed_time":2.055150676,"remaining_time":6.472445489},
{"learn":[0.2148725426],"iteration":241,"passed_time":2.063643562,"remaining_time":6.463809174},
{"learn":[0.2147811602],"iteration":242,"passed_time":2.072211016,"remaining_time":6.455406334},
{"learn":[0.2146461205],"iteration":243,"passed_time":2.080149245,"remaining_time":6.445052579},
{"learn":[0.2145243483],"iteration":244,"passed_time":2.08772734,"remaining_time":6.433608741},
{"learn":[0.2143681613],"iteration":245,"passed_time":2.095568093,"remaining_time":6.423001389},
{"learn":[0.2141953633],"iteration":246,"passed_time":2.103623052,"remaining_time":6.413069466},
{"learn":[0.214019243],"iteration":247,"passed_time":2.111505696,"remaining_time":6.402630176},
{"learn":[0.2138804338],"iteration":248,"passed_time":2.119828717,"remaining_time":6.393539624},
{"learn":[0.2137935449],"iteration":249,"passed_time":2.12737196,"remaining_time":6.382115881},
{"learn":[0.2136457061],"iteration":250,"passed_time":2.135461389,"remaining_time":6.37235291},
{"learn":[0.213418347],"iteration":251,"passed_time":2.143495568,"remaining_time":6.362439225},
{"learn":[0.2132386915],"iteration":252,"passed_time":2.152227927,"remaining_time":6.354601824},
{"learn":[0.2130018555],"iteration":253,"passed_time":2.160724358,"remaining_time":6.346064454},
{"learn":[0.2128464991],"iteration":254,"passed_time":2.168997867,"remaining_time":6.336876122},
{"learn":[0.2125969705],"iteration":255,"passed_time":2.176891113,"remaining_time":6.326589797},
{"learn":[0.2121409105],"iteration":256,"passed_time":2.184956205,"remaining_time":6.316818911},
{"learn":[0.211944218],"iteration":257,"passed_time":2.19329228,"remaining_time":6.307840588},
{"learn":[0.2116498182],"iteration":258,"passed_time":2.201628644,"remaining_time":6.298868051},
{"learn":[0.2113955618],"iteration":259,"passed_time":2.209417197,"remaining_time":6.288341253},
{"learn":[0.2112213582],"iteration":260,"passed_time":2.21730106,"remaining_time":6.278105299},
{"learn":[0.2109445065],"iteration":261,"passed_time":2.225845085,"remaining_time":6.269746843},
{"learn":[0.2107088205],"iteration":262,"passed_time":2.235040473,"remaining_time":6.263212276},
{"learn":[0.2105486937],"iteration":263,"passed_time":2.243418046,"remaining_time":6.254377584},
{"learn":[0.2103881836],"iteration":264,"passed_time":2.251712919,"remaining_time":6.245316964},
{"learn":[0.2102296753],"iteration":265,"passed_time":2.259730227,"remaining_time":6.235496191},
{"learn":[0.2100445467],"iteration":266,"passed_time":2.268239704,"remaining_time":6.227040085},
{"learn":[0.2097447589],"iteration":267,"passed_time":2.27678814,"remaining_time":6.218689994},
{"learn":[0.2096486701],"iteration":268,"passed_time":2.284610683,"remaining_time":6.208365832},
{"learn":[0.2095241507],"iteration":269,"passed_time":2.292165117,"remaining_time":6.197335318},
{"learn":[0.20940421],"iteration":270,"passed_time":2.300250513,"remaining_time":6.187758759},
{"learn":[0.2091356212],"iteration":271,"passed_time":2.308063821,"remaining_time":6.177464933},
{"learn":[0.2089962157],"iteration":272,"passed_time":2.316996733,"remaining_time":6.170170787},
{"learn":[0.2088573001],"iteration":273,"passed_time":2.324831545,"remaining_time":6.159955116},
{"learn":[0.2086747696],"iteration":274,"passed_time":2.333215401,"remaining_time":6.15120424},
{"learn":[0.2085196687],"iteration":275,"passed_time":2.340314989,"remaining_time":6.139087146},
{"learn":[0.2083770475],"iteration":276,"passed_time":2.348162478,"remaining_time":6.128958381},
{"learn":[0.2082828753],"iteration":277,"passed_time":2.355876223,"remaining_time":6.118498679},
{"learn":[0.2080075995],"iteration":278,"passed_time":2.364279294,"remaining_time":6.10984004},
{"learn":[0.2077567932],"iteration":279,"passed_time":2.372151362,"remaining_time":6.099817789},
{"learn":[0.2075680442],"iteration":280,"passed_time":2.381422847,"remaining_time":6.093391556},
{"learn":[0.2074250609],"iteration":281,"passed_time":2.389773219,"remaining_time":6.084599897},
{"learn":[0.2071350481],"iteration":282,"passed_time":2.398875586,"remaining_time":6.07771659},
{"learn":[0.2069797982],"iteration":283,"passed_time":2.406479775,"remaining_time":6.06704056},
{"learn":[0.2068118344],"iteration":284,"passed_time":2.414433009,"remaining_time":6.05726176},
{"learn":[0.2067235187],"iteration":285,"passed_time":2.421990158,"remaining_time":6.046506898},
{"learn":[0.2064631503],"iteration":286,"passed_time":2.430024504,"remaining_time":6.03695983},
{"learn":[0.2063522179],"iteration":287,"passed_time":2.437502454,"remaining_time":6.026047732},
{"learn":[0.206225867],"iteration":288,"passed_time":2.445280943,"remaining_time":6.015898791},
{"learn":[0.2061267754],"iteration":289,"passed_time":2.453789652,"remaining_time":6.007553977},
{"learn":[0.2059338098],"iteration":290,"passed_time":2.461196705,"remaining_time":5.996523931},
{"learn":[0.2058162969],"iteration":291,"passed_time":2.469051374,"remaining_time":5.986604017},
{"learn":[0.2056283146],"iteration":292,"passed_time":2.477494709,"remaining_time":5.978118633},
{"learn":[0.2054908683],"iteration":293,"passed_time":2.487818049,"remaining_time":5.974148104},
{"learn":[0.2052864879],"iteration":294,"passed_time":2.496115874,"remaining_time":5.965293868},
{"learn":[0.2050818519],"iteration":295,"passed_time":2.504640422,"remaining_time":5.956982626},
{"learn":[0.2048831149],"iteration":296,"passed_time":2.512802358,"remaining_time":5.947811643},
{"learn":[0.2047944372],"iteration":297,"passed_time":2.520366802,"remaining_time":5.937239917},
{"learn":[0.2046602919],"iteration":298,"passed_time":2.528236118,"remaining_time":5.927403074},
{"learn":[0.2045318327],"iteration":299,"passed_time":2.536158268,"remaining_time":5.917702625},
{"learn":[0.2044446457],"iteration":300,"passed_time":2.544047444,"remaining_time":5.907937419},
{"learn":[0.2043068587],"iteration":301,"passed_time":2.552543229,"remaining_time":5.899586669},
{"learn":[0.2041407051],"iteration":302,"passed_time":2.561216206,"remaining_time":5.89164256},
{"learn":[0.2039649255],"iteration":303,"passed_time":2.570433653,"remaining_time":5.884940206},
{"learn":[0.2037837367],"iteration":304,"passed_time":2.57881726,"remaining_time":5.876321297},
{"learn":[0.2037087099],"iteration":305,"passed_time":2.587533261,"remaining_time":5.868457787},
{"learn":[0.2035628091],"iteration":306,"passed_time":2.595171618,"remaining_time":5.858156128},
{"learn":[0.2034543258],"iteration":307,"passed_time":2.602518291,"remaining_time":5.84721642},
{"learn":[0.2032830184],"iteration":308,"passed_time":2.610054799,"remaining_time":5.836724486},
{"learn":[0.203089563],"iteration":309,"passed_time":2.618148491,"remaining_time":5.827491802},
{"learn":[0.2029005797],"iteration":310,"passed_time":2.62630126,"remaining_time":5.818397326},
{"learn":[0.2027707576],"iteration":311,"passed_time":2.634564079,"remaining_time":5.809551558},
{"learn":[0.2025745549],"iteration":312,"passed_time":2.642724717,"remaining_time":5.800485242},
{"learn":[0.2024218179],"iteration":313,"passed_time":2.650482743,"remaining_time":5.790545101},
{"learn":[0.202161556],"iteration":314,"passed_time":2.658554514,"remaining_time":5.781301087},
{"learn":[0.2019401385],"iteration":315,"passed_time":2.666811007,"remaining_time":5.772464331},
{"learn":[0.2018153849],"iteration":316,"passed_time":2.6751547,"remaining_time":5.763819116},
{"learn":[0.201687884],"iteration":317,"passed_time":2.683678663,"remaining_time":5.755562416},
{"learn":[0.2015886646],"iteration":318,"passed_time":2.693951896,"remaining_time":5.751038374},
{"learn":[0.2014822258],"iteration":319,"passed_time":2.702701934,"remaining_time":5.743241609},
{"learn":[0.2012767592],"iteration":320,"passed_time":2.711501524,"remaining_time":5.735543722},
{"learn":[0.2011352667],"iteration":321,"passed_time":2.720350317,"remaining_time":5.727942594},
{"learn":[0.2008488103],"iteration":322,"passed_time":2.729153042,"remaining_time":5.720237181},
{"learn":[0.2006574419],"iteration":323,"passed_time":2.737459409,"remaining_time":5.711489384},
{"learn":[0.2004207124],"iteration":324,"passed_time":2.746786081,"remaining_time":5.7048634},
{"learn":[0.2002694023],"iteration":325,"passed_time":2.755710734,"remaining_time":5.697389677},
{"learn":[0.2000979885],"iteration":326,"passed_time":2.763520834,"remaining_time":5.687613214},
{"learn":[0.1999692311],"iteration":327,"passed_time":2.771565235,"remaining_time":5.678328774},
{"learn":[0.1998588951],"iteration":328,"passed_time":2.779763134,"remaining_time":5.669364933},
{"learn":[0.1996568998],"iteration":329,"passed_time":2.788341234,"remaining_time":5.661177657},
{"learn":[0.1994997332],"iteration":330,"passed_time":2.796332705,"remaining_time":5.651802355},
{"learn":[0.1993515536],"iteration":331,"passed_time":2.804715012,"remaining_time":5.643221771},
{"learn":[0.1991312223],"iteration":332,"passed_time":2.81249643,"remaining_time":5.633438794},
{"learn":[0.1989902408],"iteration":333,"passed_time":2.82005649,"remaining_time":5.623226415},
{"learn":[0.1987713576],"iteration":334,"passed_time":2.828368017,"remaining_time":5.614521586},
{"learn":[0.1986373188],"iteration":335,"passed_time":2.836346501,"remaining_time":5.605160942},
{"learn":[0.1984215022],"iteration":336,"passed_time":2.845598068,"remaining_time":5.598313112},
{"learn":[0.1982170579],"iteration":337,"passed_time":2.854148527,"remaining_time":5.590077884},
{"learn":[0.1980476672],"iteration":338,"passed_time":2.863839561,"remaining_time":5.584064749},
{"learn":[0.197769197],"iteration":339,"passed_time":2.873742639,"remaining_time":5.578441593},
{"learn":[0.1976421646],"iteration":340,"passed_time":2.88495062,"remaining_time":5.575315127},
{"learn":[0.1975533804],"iteration":341,"passed_time":2.895948262,"remaining_time":5.571736715},
{"learn":[0.1974338444],"iteration":342,"passed_time":2.905729762,"remaining_time":5.565785579},
{"learn":[0.1973245731],"iteration":343,"passed_time":2.914894841,"remaining_time":5.558636674},
{"learn":[0.1971850611],"iteration":344,"passed_time":2.924793123,"remaining_time":5.552868103},
{"learn":[0.1969580001],"iteration":345,"passed_time":2.934538036,"remaining_time":5.546785768},
{"learn":[0.1967816456],"iteration":346,"passed_time":2.943968787,"remaining_time":5.540091118},
{"learn":[0.1966770808],"iteration":347,"passed_time":2.953286486,"remaining_time":5.533168933},
{"learn":[0.1966105299],"iteration":348,"passed_time":2.962223213,"remaining_time":5.525522383},
{"learn":[0.1964816661],"iteration":349,"passed_time":2.970810658,"remaining_time":5.517219793},
{"learn":[0.196307569],"iteration":350,"passed_time":2.979637165,"remaining_time":5.509357608},
{"learn":[0.196068582],"iteration":351,"passed_time":2.988699256,"remaining_time":5.501923631},
{"learn":[0.1958653516],"iteration":352,"passed_time":2.999262708,"remaining_time":5.497232216},
{"learn":[0.1957227091],"iteration":353,"passed_time":3.008243834,"remaining_time":5.489620104},
{"learn":[0.1956424647],"iteration":354,"passed_time":3.017067876,"remaining_time":5.481714874},
{"learn":[0.1955355573],"iteration":355,"passed_time":3.026145499,"remaining_time":5.474263205},
{"learn":[0.1954118685],"iteration":356,"passed_time":3.035045137,"remaining_time":5.466481857},
{"learn":[0.1952181787],"iteration":357,"passed_time":3.043509973,"remaining_time":5.457914532},
{"learn":[0.194978702],"iteration":358,"passed_time":3.051785183,"remaining_time":5.449009199},
{"learn":[0.1948394882],"iteration":359,"passed_time":3.060521176,"remaining_time":5.440926534},
{"learn":[0.1947326873],"iteration":360,"passed_time":3.068521194,"remaining_time":5.431537515},
{"learn":[0.1945951985],"iteration":361,"passed_time":3.076981929,"remaining_time":5.422968151},
{"learn":[0.19446593],"iteration":362,"passed_time":3.086128227,"remaining_time":5.415602426},
{"learn":[0.1943350856],"iteration":363,"passed_time":3.09525543,"remaining_time":5.408193554},
{"learn":[0.1942633598],"iteration":364,"passed_time":3.105140024,"remaining_time":5.402092919},
{"learn":[0.1941596894],"iteration":365,"passed_time":3.112956982,"remaining_time":5.392389964},
{"learn":[0.1939705358],"iteration":366,"passed_time":3.12069954,"remaining_time":5.382568961},
{"learn":[0.1938188211],"iteration":367,"passed_time":3.129278667,"remaining_time":5.374195972},
{"learn":[0.1936418063],"iteration":368,"passed_time":3.139273277,"remaining_time":5.368242378},
{"learn":[0.1934743749],"iteration":369,"passed_time":3.147227248,"remaining_time":5.358792342},
{"learn":[0.193400775],"iteration":370,"passed_time":3.15468203,"remaining_time":5.348504035},
{"learn":[0.1932318315],"iteration":371,"passed_time":3.162589791,"remaining_time":5.338995668},
{"learn":[0.1930104992],"iteration":372,"passed_time":3.170721786,"remaining_time":5.329872814},
{"learn":[0.1928357419],"iteration":373,"passed_time":3.178818022,"remaining_time":5.320695406},
{"learn":[0.1925749902],"iteration":374,"passed_time":3.186431208,"remaining_time":5.31071868},
{"learn":[0.1923783829],"iteration":375,"passed_time":3.19464809,"remaining_time":5.301756404},
{"learn":[0.1922134218],"iteration":376,"passed_time":3.20276349,"remaining_time":5.292630383},
{"learn":[0.1920523154],"iteration":377,"passed_time":3.21105522,"remaining_time":5.283799859},
{"learn":[0.1919514349],"iteration":378,"passed_time":3.218669954,"remaining_time":5.273862905},
{"learn":[0.1917494184],"iteration":379,"passed_time":3.22683533,"remaining_time":5.264836591},
{"learn":[0.1916112055],"iteration":380,"passed_time":3.235123767,"remaining_time":5.256014729},
{"learn":[0.1914339352],"iteration":381,"passed_time":3.24305802,"remaining_time":5.246622661},
{"learn":[0.191324025],"iteration":382,"passed_time":3.250862279,"remaining_time":5.237028789},
{"learn":[0.1911901779],"iteration":383,"passed_time":3.259461372,"remaining_time":5.228719284},
{"learn":[0.1909510206],"iteration":384,"passed_time":3.267494079,"remaining_time":5.219503528},
{"learn":[0.1908616188],"iteration":385,"passed_time":3.275821036,"remaining_time":5.210761959},
{"learn":[0.1907663818],"iteration":386,"passed_time":3.28370865,"remaining_time":5.201326622},
{"learn":[0.1906672263],"iteration":387,"passed_time":3.292989974,"remaining_time":5.194097589},
{"learn":[0.1905160439],"iteration":388,"passed_time":3.30118572,"remaining_time":5.185152892},
{"learn":[0.1904123097],"iteration":389,"passed_time":3.310142427,"remaining_time":5.177402257},
{"learn":[0.1902116774],"iteration":390,"passed_time":3.318546667,"remaining_time":5.168784962},
{"learn":[0.1900516145],"iteration":391,"passed_time":3.326249388,"remaining_time":5.159080683},
{"learn":[0.1898083258],"iteration":392,"passed_time":3.334545515,"remaining_time":5.150303123},
{"learn":[0.1896914304],"iteration":393,"passed_time":3.341893359,"remaining_time":5.140069481},
{"learn":[0.1895380972],"iteration":394,"passed_time":3.349822307,"remaining_time":5.130740495},
{"learn":[0.1894594713],"iteration":395,"passed_time":3.358840938,"remaining_time":5.123080622},
{"learn":[0.189323814],"iteration":396,"passed_time":3.366768688,"remaining_time":5.113756974},
{"learn":[0.1892160334],"iteration":397,"passed_time":3.374975028,"remaining_time":5.104861726},
{"learn":[0.1890177437],"iteration":398,"passed_time":3.383433813,"remaining_time":5.096350179},
{"learn":[0.1888644531],"iteration":399,"passed_time":3.398843935,"remaining_time":5.098265903},
{"learn":[0.1886759596],"iteration":400,"passed_time":3.419242154,"remaining_time":5.10754626},
{"learn":[0.1885844069],"iteration":401,"passed_time":3.433513068,"remaining_time":5.107564216},
{"learn":[0.188403644],"iteration":402,"passed_time":3.444788858,"remaining_time":5.103074313},
{"learn":[0.1882900922],"iteration":403,"passed_time":3.454602638,"remaining_time":5.096393991},
{"learn":[0.1881418275],"iteration":404,"passed_time":3.465439864,"remaining_time":5.091201775},
{"learn":[0.1880304053],"iteration":405,"passed_time":3.4752012,"remaining_time":5.084407667},
{"learn":[0.1879041183],"iteration":406,"passed_time":3.483171068,"remaining_time":5.074988804},
{"learn":[0.1877587286],"iteration":407,"passed_time":3.490770606,"remaining_time":5.065039703},
{"learn":[0.1876432814],"iteration":408,"passed_time":3.499521568,"remaining_time":5.056765884},
{"learn":[0.1875116065],"iteration":409,"passed_time":3.508244014,"remaining_time":5.048448703},
{"learn":[0.1873795908],"iteration":410,"passed_time":3.517131897,"remaining_time":5.040366636},
{"learn":[0.187252452],"iteration":411,"passed_time":3.525861755,"remaining_time":5.032055125},
{"learn":[0.1871495057],"iteration":412,"passed_time":3.534829306,"remaining_time":5.024079425},
{"learn":[0.1871059974],"iteration":413,"passed_time":3.544011521,"remaining_time":5.016402781},
{"learn":[0.1869665706],"iteration":414,"passed_time":3.55430764,"remaining_time":5.010289083},
{"learn":[0.1868501012],"iteration":415,"passed_time":3.563802401,"remaining_time":5.003030294},
{"learn":[0.1866763235],"iteration":416,"passed_time":3.572451672,"remaining_time":4.994578717},
{"learn":[0.1865069542],"iteration":417,"passed_time":3.580860293,"remaining_time":4.985791125},
{"learn":[0.1863046608],"iteration":418,"passed_time":3.590001358,"remaining_time":4.978020976},
{"learn":[0.1861289451],"iteration":419,"passed_time":3.599119819,"remaining_time":4.970213083},
{"learn":[0.1860325155],"iteration":420,"passed_time":3.608872613,"remaining_time":4.963271361},
{"learn":[0.1858374202],"iteration":421,"passed_time":3.6177902,"remaining_time":4.955172359},
{"learn":[0.1855119491],"iteration":422,"passed_time":3.626735916,"remaining_time":4.947107857},
{"learn":[0.1853583177],"iteration":423,"passed_time":3.641070282,"remaining_time":4.946359628},
{"learn":[0.185217464],"iteration":424,"passed_time":3.649850104,"remaining_time":4.938032494},
{"learn":[0.1851023789],"iteration":425,"passed_time":3.659074361,"remaining_time":4.930302074},
{"learn":[0.1849459577],"iteration":426,"passed_time":3.670758486,"remaining_time":4.925865603},
{"learn":[0.1848354087],"iteration":427,"passed_time":3.680439835,"remaining_time":4.918718659},
{"learn":[0.1847099735],"iteration":428,"passed_time":3.690252404,"remaining_time":4.911734552},
{"learn":[0.1845069773],"iteration":429,"passed_time":3.699150576,"remaining_time":4.903525182},
{"learn":[0.1844260728],"iteration":430,"passed_time":3.708164802,"remaining_time":4.895465829},
{"learn":[0.1842547015],"iteration":431,"passed_time":3.717831966,"remaining_time":4.888260548},
{"learn":[0.1840601813],"iteration":432,"passed_time":3.726742899,"remaining_time":4.880053635},
{"learn":[0.1838760962],"iteration":433,"passed_time":3.735712149,"remaining_time":4.871919531},
{"learn":[0.1837099851],"iteration":434,"passed_time":3.743966482,"remaining_time":4.862853016},
{"learn":[0.1835787148],"iteration":435,"passed_time":3.752885429,"remaining_time":4.854649959},
{"learn":[0.1834781112],"iteration":436,"passed_time":3.761559365,"remaining_time":4.846127969},
{"learn":[0.1834118371],"iteration":437,"passed_time":3.769785484,"remaining_time":4.837030689},
{"learn":[0.1834012316],"iteration":438,"passed_time":3.778058452,"remaining_time":4.827997248},
{"learn":[0.1832982001],"iteration":439,"passed_time":3.786431598,"remaining_time":4.819094761},
{"learn":[0.1832374631],"iteration":440,"passed_time":3.795094802,"remaining_time":4.810562346},
{"learn":[0.1830868132],"iteration":441,"passed_time":3.803827114,"remaining_time":4.802116582},
{"learn":[0.1828362411],"iteration":442,"passed_time":3.812461586,"remaining_time":4.793546508},
{"learn":[0.1827580837],"iteration":443,"passed_time":3.822158871,"remaining_time":4.786307055},
{"learn":[0.1826259403],"iteration":444,"passed_time":3.830331882,"remaining_time":4.777155493},
{"learn":[0.1824060774],"iteration":445,"passed_time":3.83931153,"remaining_time":4.769010286},
{"learn":[0.1821914321],"iteration":446,"passed_time":3.848724218,"remaining_time":4.761397075},
{"learn":[0.1820154183],"iteration":447,"passed_time":3.857583861,"remaining_time":4.753094401},
{"learn":[0.1819078721],"iteration":448,"passed_time":3.866215188,"remaining_time":4.744509061},
{"learn":[0.1818300555],"iteration":449,"passed_time":3.874032871,"remaining_time":4.734929064},
{"learn":[0.1815584639],"iteration":450,"passed_time":3.882696839,"remaining_time":4.726387062},
{"learn":[0.1814761964],"iteration":451,"passed_time":3.89151042,"remaining_time":4.718025908},
{"learn":[0.1813398363],"iteration":452,"passed_time":3.900246967,"remaining_time":4.709569738},
{"learn":[0.1812132937],"iteration":453,"passed_time":3.908743094,"remaining_time":4.700823192},
{"learn":[0.1810567234],"iteration":454,"passed_time":3.928442397,"remaining_time":4.705496937},
{"learn":[0.1809162957],"iteration":455,"passed_time":3.941628654,"remaining_time":4.702293832},
{"learn":[0.1808013597],"iteration":456,"passed_time":3.955524815,"remaining_time":4.699890535},
{"learn":[0.1806209162],"iteration":457,"passed_time":3.974172023,"remaining_time":4.703059469},
{"learn":[0.1805128376],"iteration":458,"passed_time":3.988164385,"remaining_time":4.700646912},
{"learn":[0.1804417506],"iteration":459,"passed_time":3.996850323,"remaining_time":4.691954727},
{"learn":[0.1802729136],"iteration":460,"passed_time":4.009410331,"remaining_time":4.687792122},
{"learn":[0.1801309526],"iteration":461,"passed_time":4.021597778,"remaining_time":4.683159317},
{"learn":[0.1799881397],"iteration":462,"passed_time":4.03254837,"remaining_time":4.67705934},
{"learn":[0.1798620018],"iteration":463,"passed_time":4.042183772,"remaining_time":4.669419185},
{"learn":[0.1796950602],"iteration":464,"passed_time":4.051933592,"remaining_time":4.66190209},
{"learn":[0.1794902325],"iteration":465,"passed_time":4.060894714,"remaining_time":4.653471626},
{"learn":[0.1792382335],"iteration":466,"passed_time":4.070323882,"remaining_time":4.645573082},
{"learn":[0.1790845382],"iteration":467,"passed_time":4.079400565,"remaining_time":4.637267308},
{"learn":[0.1789443874],"iteration":468,"passed_time":4.088012869,"remaining_time":4.62843248},
{"learn":[0.1787870291],"iteration":469,"passed_time":4.097197914,"remaining_time":4.620244457},
{"learn":[0.1785704459],"iteration":470,"passed_time":4.106331825,"remaining_time":4.611994767},
{"learn":[0.178463283],"iteration":471,"passed_time":4.116808551,"remaining_time":4.605243464},
{"learn":[0.1783203423],"iteration":472,"passed_time":4.127780052,"remaining_time":4.599027669},
{"learn":[0.1782769831],"iteration":473,"passed_time":4.138549172,"remaining_time":4.592567225},
{"learn":[0.178121435],"iteration":474,"passed_time":4.148065202,"remaining_time":4.584703645},
{"learn":[0.1780460249],"iteration":475,"passed_time":4.156986181,"remaining_time":4.576178064},
{"learn":[0.1779630545],"iteration":476,"passed_time":4.165613129,"remaining_time":4.567328441},
{"learn":[0.1777906611],"iteration":477,"passed_time":4.174126745,"remaining_time":4.558355985},
{"learn":[0.177680325],"iteration":478,"passed_time":4.182933335,"remaining_time":4.549704107},
{"learn":[0.1775126807],"iteration":479,"passed_time":4.1918466,"remaining_time":4.54116715},
{"learn":[0.1774005877],"iteration":480,"passed_time":4.200196383,"remaining_time":4.532020629},
{"learn":[0.1773132409],"iteration":481,"passed_time":4.208535197,"remaining_time":4.522865626},
{"learn":[0.1772449225],"iteration":482,"passed_time":4.217362036,"remaining_time":4.514236383},
{"learn":[0.1772152993],"iteration":483,"passed_time":4.227170274,"remaining_time":4.506652606},
{"learn":[0.1769283851],"iteration":484,"passed_time":4.236439486,"remaining_time":4.498487289},
{"learn":[0.1768119796],"iteration":485,"passed_time":4.245289911,"remaining_time":4.489874515},
{"learn":[0.1766226876],"iteration":486,"passed_time":4.254158126,"remaining_time":4.481279505},
{"learn":[0.176402846],"iteration":487,"passed_time":4.263674763,"remaining_time":4.473363686},
{"learn":[0.1763209618],"iteration":488,"passed_time":4.272179673,"remaining_time":4.464384075},
{"learn":[0.176160473],"iteration":489,"passed_time":4.280999049,"remaining_time":4.455733704},
{"learn":[0.1760511165],"iteration":490,"passed_time":4.289303996,"remaining_time":4.446549356},
{"learn":[0.1759174717],"iteration":491,"passed_time":4.297946882,"remaining_time":4.437717512},
{"learn":[0.1758645611],"iteration":492,"passed_time":4.306406546,"remaining_time":4.42869801},
{"learn":[0.1757434065],"iteration":493,"passed_time":4.315513512,"remaining_time":4.4203438},
{"learn":[0.1755450955],"iteration":494,"passed_time":4.324353406,"remaining_time":4.411714081},
{"learn":[0.1753630761],"iteration":495,"passed_time":4.332814604,"remaining_time":4.40269871},
{"learn":[0.1751335128],"iteration":496,"passed_time":4.342560035,"remaining_time":4.394985307},
{"learn":[0.175053705],"iteration":497,"passed_time":4.351457918,"remaining_time":4.386409387},
{"learn":[0.1748495907],"iteration":498,"passed_time":4.360689367,"remaining_time":4.37816708},
{"learn":[0.174709344],"iteration":499,"passed_time":4.369385508,"remaining_time":4.369385508},
{"learn":[0.1745314561],"iteration":500,"passed_time":4.377793641,"remaining_time":4.360317419},
{"learn":[0.1743470303],"iteration":501,"passed_time":4.387394182,"remaining_time":4.352434866},
{"learn":[0.1741753184],"iteration":502,"passed_time":4.397040997,"remaining_time":4.344591204},
{"learn":[0.1740605101],"iteration":503,"passed_time":4.406369539,"remaining_time":4.336427165},
{"learn":[0.1739280259],"iteration":504,"passed_time":4.416092549,"remaining_time":4.328645172},
{"learn":[0.173769113],"iteration":505,"passed_time":4.424946316,"remaining_time":4.320006877},
{"learn":[0.1736800093],"iteration":506,"passed_time":4.433634956,"remaining_time":4.311207166},
{"learn":[0.1735977631],"iteration":507,"passed_time":4.441960874,"remaining_time":4.302056594},
{"learn":[0.1735147714],"iteration":508,"passed_time":4.453267723,"remaining_time":4.295784778},
{"learn":[0.1734145298],"iteration":509,"passed_time":4.463459978,"remaining_time":4.288422331},
{"learn":[0.173256128],"iteration":510,"passed_time":4.472087731,"remaining_time":4.279551664},
{"learn":[0.17315496],"iteration":511,"passed_time":4.481943634,"remaining_time":4.271852526},
{"learn":[0.1730537707],"iteration":512,"passed_time":4.490646166,"remaining_time":4.263050064},
{"learn":[0.1729516125],"iteration":513,"passed_time":4.498671937,"remaining_time":4.253608096},
{"learn":[0.1727684218],"iteration":514,"passed_time":4.507452994,"remaining_time":4.244882917},
{"learn":[0.1726389936],"iteration":515,"passed_time":4.517406205,"remaining_time":4.237256983},
{"learn":[0.1724921983],"iteration":516,"passed_time":4.527667902,"remaining_time":4.229910245},
{"learn":[0.1724091109],"iteration":517,"passed_time":4.536379347,"remaining_time":4.22110974},
{"learn":[0.1722732193],"iteration":518,"passed_time":4.544862747,"remaining_time":4.212098229},
{"learn":[0.1721578679],"iteration":519,"passed_time":4.553751913,"remaining_time":4.203463305},
{"learn":[0.1718950292],"iteration":520,"passed_time":4.562282356,"remaining_time":4.194497598},
{"learn":[0.1717167686],"iteration":521,"passed_time":4.570440265,"remaining_time":4.185192426},
{"learn":[0.1715950816],"iteration":522,"passed_time":4.578640659,"remaining_time":4.175930391},
{"learn":[0.1714837979],"iteration":523,"passed_time":4.587161613,"remaining_time":4.166963603},
{"learn":[0.1714031808],"iteration":524,"passed_time":4.595715985,"remaining_time":4.158028748},
{"learn":[0.1712745406],"iteration":525,"passed_time":4.604133777,"remaining_time":4.148972263},
{"learn":[0.1712039434],"iteration":526,"passed_time":4.612620934,"remaining_time":4.139980459},
{"learn":[0.1711525661],"iteration":527,"passed_time":4.620496811,"remaining_time":4.130444119},
{"learn":[0.1709953782],"iteration":528,"passed_time":4.629943553,"remaining_time":4.122312691},
{"learn":[0.1708947745],"iteration":529,"passed_time":4.63841431,"remaining_time":4.113310803},
{"learn":[0.1707773894],"iteration":530,"passed_time":4.647249273,"remaining_time":4.104632597},
{"learn":[0.1706044529],"iteration":531,"passed_time":4.656762065,"remaining_time":4.096550087},
{"learn":[0.1705280525],"iteration":532,"passed_time":4.665299687,"remaining_time":4.087607793},
{"learn":[0.1702839119],"iteration":533,"passed_time":4.674354368,"remaining_time":4.079118231},
{"learn":[0.1701361156],"iteration":534,"passed_time":4.682688329,"remaining_time":4.070000136},
{"learn":[0.1700062828],"iteration":535,"passed_time":4.690845851,"remaining_time":4.060732229},
{"learn":[0.1697765066],"iteration":536,"passed_time":4.699615281,"remaining_time":4.051996043},
{"learn":[0.1696203409],"iteration":537,"passed_time":4.707704543,"remaining_time":4.042675649},
{"learn":[0.169524465],"iteration":538,"passed_time":4.715020585,"remaining_time":4.032698496},
{"learn":[0.1693726438],"iteration":539,"passed_time":4.723195074,"remaining_time":4.02346247},
{"learn":[0.169302973],"iteration":540,"passed_time":4.731744901,"remaining_time":4.014548816},
{"learn":[0.1691980888],"iteration":541,"passed_time":4.740081279,"remaining_time":4.005456136},
{"learn":[0.1690856444],"iteration":542,"passed_time":4.748222086,"remaining_time":3.996201645},
{"learn":[0.169015143],"iteration":543,"passed_time":4.756027598,"remaining_time":3.986670192},
{"learn":[0.1689377097],"iteration":544,"passed_time":4.764288405,"remaining_time":3.977525182},
{"learn":[0.1688403218],"iteration":545,"passed_time":4.772656791,"remaining_time":3.968472863},
{"learn":[0.1687561376],"iteration":546,"passed_time":4.780950115,"remaining_time":3.959360882},
{"learn":[0.168682889],"iteration":547,"passed_time":4.788722231,"remaining_time":3.949821986},
{"learn":[0.168575428],"iteration":548,"passed_time":4.797105603,"remaining_time":3.94079167},
{"learn":[0.1685018386],"iteration":549,"passed_time":4.805518697,"remaining_time":3.931788025},
{"learn":[0.1683164971],"iteration":550,"passed_time":4.813351915,"remaining_time":3.922313992},
{"learn":[0.1682474119],"iteration":551,"passed_time":4.821094114,"remaining_time":3.912772034},
{"learn":[0.1681019476],"iteration":552,"passed_time":4.830025079,"remaining_time":3.904197487},
{"learn":[0.1679888324],"iteration":553,"passed_time":4.838622653,"remaining_time":3.895353255},
{"learn":[0.1678542292],"iteration":554,"passed_time":4.847217684,"remaining_time":3.886507873},
{"learn":[0.1677450325],"iteration":555,"passed_time":4.855381626,"remaining_time":3.87731914},
{"learn":[0.16757939],"iteration":556,"passed_time":4.863298352,"remaining_time":3.867937469},
{"learn":[0.1674114262],"iteration":557,"passed_time":4.870806295,"remaining_time":3.858237244},
{"learn":[0.1672658767],"iteration":558,"passed_time":4.878314238,"remaining_time":3.848544864},
{"learn":[0.167161461],"iteration":559,"passed_time":4.886695526,"remaining_time":3.839546484},
{"learn":[0.1669938273],"iteration":560,"passed_time":4.894245001,"remaining_time":3.829899386},
{"learn":[0.1668843431],"iteration":561,"passed_time":4.90183186,"remaining_time":3.820288887},
{"learn":[0.1667285821],"iteration":562,"passed_time":4.909508599,"remaining_time":3.810755342},
{"learn":[0.1665657933],"iteration":563,"passed_time":4.918039995,"remaining_time":3.801889074},
{"learn":[0.1664600678],"iteration":564,"passed_time":4.926574207,"remaining_time":3.79302616},
{"learn":[0.1663501258],"iteration":565,"passed_time":4.936032414,"remaining_time":3.784872911},
{"learn":[0.1661377379],"iteration":566,"passed_time":4.944803812,"remaining_time":3.776190565},
{"learn":[0.1659860658],"iteration":567,"passed_time":4.954502687,"remaining_time":3.768213311},
{"learn":[0.1658389404],"iteration":568,"passed_time":4.963621187,"remaining_time":3.75979039},
{"learn":[0.1657429261],"iteration":569,"passed_time":4.9713847,"remaining_time":3.750342844},
{"learn":[0.1655559873],"iteration":570,"passed_time":4.981244416,"remaining_time":3.742476103},
{"learn":[0.1653574207],"iteration":571,"passed_time":4.990242577,"remaining_time":3.733957732},
{"learn":[0.1652335508],"iteration":572,"passed_time":5.000837359,"remaining_time":3.726627491},
{"learn":[0.165165424],"iteration":573,"passed_time":5.01041655,"remaining_time":3.718532143},
{"learn":[0.1650606037],"iteration":574,"passed_time":5.019110725,"remaining_time":3.709777493},
{"learn":[0.1649577746],"iteration":575,"passed_time":5.028371877,"remaining_time":3.701440409},
{"learn":[0.1648133006],"iteration":576,"passed_time":5.036373363,"remaining_time":3.692176659},
{"learn":[0.1647022404],"iteration":577,"passed_time":5.044334875,"remaining_time":3.682888092},
{"learn":[0.1646035109],"iteration":578,"passed_time":5.051938305,"remaining_time":3.673343742},
{"learn":[0.1644743489],"iteration":579,"passed_time":5.060140167,"remaining_time":3.664239431},
{"learn":[0.1643688258],"iteration":580,"passed_time":5.068259989,"remaining_time":3.655079062},
{"learn":[0.1642451582],"iteration":581,"passed_time":5.076601254,"remaining_time":3.646081313},
{"learn":[0.1640803463],"iteration":582,"passed_time":5.084171516,"remaining_time":3.636534343},
{"learn":[0.163949651],"iteration":583,"passed_time":5.092149317,"remaining_time":3.627284445},
{"learn":[0.1638429885],"iteration":584,"passed_time":5.100472443,"remaining_time":3.61828387},
{"learn":[0.1637347502],"iteration":585,"passed_time":5.108061195,"remaining_time":3.608766783},
{"learn":[0.1635477262],"iteration":586,"passed_time":5.116155701,"remaining_time":3.599612103},
{"learn":[0.1633321865],"iteration":587,"passed_time":5.124310057,"remaining_time":3.590502965},
{"learn":[0.1632164837],"iteration":588,"passed_time":5.132477193,"remaining_time":3.581405987},
{"learn":[0.1630610208],"iteration":589,"passed_time":5.140375125,"remaining_time":3.572125087},
{"learn":[0.1629140871],"iteration":590,"passed_time":5.148758517,"remaining_time":3.563184828},
{"learn":[0.1628180622],"iteration":591,"passed_time":5.156903303,"remaining_time":3.554082006},
{"learn":[0.1626840553],"iteration":592,"passed_time":5.165400778,"remaining_time":3.54522448},
{"learn":[0.1625501229],"iteration":593,"passed_time":5.174764549,"remaining_time":3.536960281},
{"learn":[0.1624690267],"iteration":594,"passed_time":5.182699282,"remaining_time":3.527719679},
{"learn":[0.1623331138],"iteration":595,"passed_time":5.191533554,"remaining_time":3.519093214},
{"learn":[0.1622374296],"iteration":596,"passed_time":5.199787385,"remaining_time":3.510074231},
{"learn":[0.1621703889],"iteration":597,"passed_time":5.20827918,"remaining_time":3.501217776},
{"learn":[0.1620542815],"iteration":598,"passed_time":5.216724067,"remaining_time":3.492331137},
{"learn":[0.161913545],"iteration":599,"passed_time":5.225368344,"remaining_time":3.483578896},
{"learn":[0.161753759],"iteration":600,"passed_time":5.233263548,"remaining_time":3.47432971},
{"learn":[0.1616012882],"iteration":601,"passed_time":5.241463148,"remaining_time":3.465286267},
{"learn":[0.1615193827],"iteration":602,"passed_time":5.249247377,"remaining_time":3.455972154},
{"learn":[0.1614094832],"iteration":603,"passed_time":5.257561799,"remaining_time":3.447010716},
{"learn":[0.1612572467],"iteration":604,"passed_time":5.265444572,"remaining_time":3.437769597},
{"learn":[0.1610931056],"iteration":605,"passed_time":5.273532696,"remaining_time":3.428666472},
{"learn":[0.1609907024],"iteration":606,"passed_time":5.282936203,"remaining_time":3.420418332},
{"learn":[0.1608930802],"iteration":607,"passed_time":5.291787189,"remaining_time":3.411810161},
{"learn":[0.1607643548],"iteration":608,"passed_time":5.300818002,"remaining_time":3.403316648},
{"learn":[0.1607032558],"iteration":609,"passed_time":5.308570422,"remaining_time":3.39400404},
{"learn":[0.160572241],"iteration":610,"passed_time":5.316732288,"remaining_time":3.384957218},
{"learn":[0.1604790378],"iteration":611,"passed_time":5.324912483,"remaining_time":3.375924907},
{"learn":[0.1603908179],"iteration":612,"passed_time":5.333081482,"remaining_time":3.366888309},
{"learn":[0.16024595],"iteration":613,"passed_time":5.341116738,"remaining_time":3.357770457},
{"learn":[0.1601282347],"iteration":614,"passed_time":5.349249313,"remaining_time":3.348717049},
{"learn":[0.1600439547],"iteration":615,"passed_time":5.356733721,"remaining_time":3.339262579},
{"learn":[0.1598996298],"iteration":616,"passed_time":5.36486819,"remaining_time":3.330218017},
{"learn":[0.1598354427],"iteration":617,"passed_time":5.373008642,"remaining_time":3.321180099},
{"learn":[0.1596945891],"iteration":618,"passed_time":5.381072396,"remaining_time":3.312097872},
{"learn":[0.1595296281],"iteration":619,"passed_time":5.389930581,"remaining_time":3.30350584},
{"learn":[0.1594177267],"iteration":620,"passed_time":5.398547873,"remaining_time":3.294765932},
{"learn":[0.1593002458],"iteration":621,"passed_time":5.40659723,"remaining_time":3.285681275},
{"learn":[0.1592113125],"iteration":622,"passed_time":5.414574663,"remaining_time":3.276556417},
{"learn":[0.1590398135],"iteration":623,"passed_time":5.422164554,"remaining_time":3.267201718},
{"learn":[0.1589896394],"iteration":624,"passed_time":5.429886994,"remaining_time":3.257932197},
{"learn":[0.158896596],"iteration":625,"passed_time":5.438231604,"remaining_time":3.249039329},
{"learn":[0.15879119],"iteration":626,"passed_time":5.445674496,"remaining_time":3.239611781},
{"learn":[0.1586590146],"iteration":627,"passed_time":5.453205505,"remaining_time":3.230242751},
{"learn":[0.1584813184],"iteration":628,"passed_time":5.461640409,"remaining_time":3.221412705},
{"learn":[0.1583738147],"iteration":629,"passed_time":5.471185363,"remaining_time":3.213235848},
{"learn":[0.1581880046],"iteration":630,"passed_time":5.479684263,"remaining_time":3.204442937},
{"learn":[0.1580206797],"iteration":631,"passed_time":5.487700049,"remaining_time":3.195369649},
{"learn":[0.1578898353],"iteration":632,"passed_time":5.496050732,"remaining_time":3.186493868},
{"learn":[0.1578278525],"iteration":633,"passed_time":5.504925942,"remaining_time":3.177922547},
{"learn":[0.1577320086],"iteration":634,"passed_time":5.513107528,"remaining_time":3.168951571},
{"learn":[0.1575929651],"iteration":635,"passed_time":5.520966745,"remaining_time":3.159798577},
{"learn":[0.1574411332],"iteration":636,"passed_time":5.528753353,"remaining_time":3.150608269},
{"learn":[0.1573355249],"iteration":637,"passed_time":5.536666312,"remaining_time":3.141494052},
{"learn":[0.1571966093],"iteration":638,"passed_time":5.544136822,"remaining_time":3.132133635},
{"learn":[0.1570025256],"iteration":639,"passed_time":5.551626566,"remaining_time":3.122789943},
{"learn":[0.1568685719],"iteration":640,"passed_time":5.559052923,"remaining_time":3.113416536},
{"learn":[0.1567663178],"iteration":641,"passed_time":5.567303991,"remaining_time":3.104509079},
{"learn":[0.1566901942],"iteration":642,"passed_time":5.575048821,"remaining_time":3.095322596},
{"learn":[0.1565995998],"iteration":643,"passed_time":5.58288584,"remaining_time":3.086191551},
{"learn":[0.1565453475],"iteration":644,"passed_time":5.591045498,"remaining_time":3.077242096},
{"learn":[0.1564431893],"iteration":645,"passed_time":5.598405853,"remaining_time":3.067857077},
{"learn":[0.1562368389],"iteration":646,"passed_time":5.606765653,"remaining_time":3.05902361},
{"learn":[0.1560861464],"iteration":647,"passed_time":5.615238804,"remaining_time":3.050253177},
{"learn":[0.1559972344],"iteration":648,"passed_time":5.623131673,"remaining_time":3.041169826},
{"learn":[0.1559123048],"iteration":649,"passed_time":5.630706987,"remaining_time":3.031919147},
{"learn":[0.1557599512],"iteration":650,"passed_time":5.638396548,"remaining_time":3.022734862},
{"learn":[0.1556242193],"iteration":651,"passed_time":5.646462352,"remaining_time":3.01375598},
{"learn":[0.1554669888],"iteration":652,"passed_time":5.654082112,"remaining_time":3.004542868},
{"learn":[0.1553416708],"iteration":653,"passed_time":5.662551311,"remaining_time":2.995784027},
{"learn":[0.1552152347],"iteration":654,"passed_time":5.670508542,"remaining_time":2.986756408},
{"learn":[0.1550767663],"iteration":655,"passed_time":5.679129052,"remaining_time":2.978079869},
{"learn":[0.1549152659],"iteration":656,"passed_time":5.687006029,"remaining_time":2.969015324},
{"learn":[0.1547686516],"iteration":657,"passed_time":5.695273741,"remaining_time":2.960157476},
{"learn":[0.1546698156],"iteration":658,"passed_time":5.703415501,"remaining_time":2.951236245},
{"learn":[0.1545385666],"iteration":659,"passed_time":5.7116223,"remaining_time":2.942350882},
{"learn":[0.1543939541],"iteration":660,"passed_time":5.719819714,"remaining_time":2.933462758},
{"learn":[0.154304712],"iteration":661,"passed_time":5.727583021,"remaining_time":2.924355077},
{"learn":[0.1541548075],"iteration":662,"passed_time":5.735660756,"remaining_time":2.915411274},
{"learn":[0.1540286802],"iteration":663,"passed_time":5.744400243,"remaining_time":2.906804942},
{"learn":[0.1539693168],"iteration":664,"passed_time":5.754079727,"remaining_time":2.898671742},
{"learn":[0.153882428],"iteration":665,"passed_time":5.762467533,"remaining_time":2.88988612},
{"learn":[0.1537462063],"iteration":666,"passed_time":5.770634836,"remaining_time":2.880991605},
{"learn":[0.1536619156],"iteration":667,"passed_time":5.779231072,"remaining_time":2.872312449},
{"learn":[0.15358083],"iteration":668,"passed_time":5.787544265,"remaining_time":2.8634935},
{"learn":[0.1534708453],"iteration":669,"passed_time":5.795958813,"remaining_time":2.854725982},
{"learn":[0.1533436958],"iteration":670,"passed_time":5.812342679,"remaining_time":2.849866977},
{"learn":[0.1532376403],"iteration":671,"passed_time":5.820295271,"remaining_time":2.840858406},
{"learn":[0.1530786422],"iteration":672,"passed_time":5.828180334,"remaining_time":2.831820162},
{"learn":[0.1530091525],"iteration":673,"passed_time":5.835604689,"remaining_time":2.822562505},
{"learn":[0.1529204321],"iteration":674,"passed_time":5.843292594,"remaining_time":2.813437175},
{"learn":[0.1528243113],"iteration":675,"passed_time":5.851713628,"remaining_time":2.804667479},
{"learn":[0.1527418095],"iteration":676,"passed_time":5.859457032,"remaining_time":2.795575512},
{"learn":[0.1526123814],"iteration":677,"passed_time":5.866853876,"remaining_time":2.786322932},
{"learn":[0.1524899171],"iteration":678,"passed_time":5.874490013,"remaining_time":2.777188946},
{"learn":[0.152365025],"iteration":679,"passed_time":5.882179781,"remaining_time":2.768084603},
{"learn":[0.1522018848],"iteration":680,"passed_time":5.890236762,"remaining_time":2.759156427},
{"learn":[0.1521254205],"iteration":681,"passed_time":5.898583906,"remaining_time":2.750366103},
{"learn":[0.1520237307],"iteration":682,"passed_time":5.906957069,"remaining_time":2.741589152},
{"learn":[0.1519169192],"iteration":683,"passed_time":5.915220809,"remaining_time":2.73276283},
{"learn":[0.1518380164],"iteration":684,"passed_time":5.922883014,"remaining_time":2.723661532},
{"learn":[0.1517139762],"iteration":685,"passed_time":5.930671511,"remaining_time":2.714622237},
{"learn":[0.1516533031],"iteration":686,"passed_time":5.938871172,"remaining_time":2.705773911},
{"learn":[0.1515509744],"iteration":687,"passed_time":5.946576263,"remaining_time":2.696703189},
{"learn":[0.1514344625],"iteration":688,"passed_time":5.95491424,"remaining_time":2.687922102},
{"learn":[0.1513120088],"iteration":689,"passed_time":5.963232873,"remaining_time":2.67913361},
{"learn":[0.1512541468],"iteration":690,"passed_time":5.971673502,"remaining_time":2.670401031},
{"learn":[0.151113996],"iteration":691,"passed_time":5.980499096,"remaining_time":2.661840638},
{"learn":[0.1510174705],"iteration":692,"passed_time":5.989099148,"remaining_time":2.653179565},
{"learn":[0.1508862322],"iteration":693,"passed_time":5.998027327,"remaining_time":2.644663346},
{"learn":[0.15074491],"iteration":694,"passed_time":6.007071832,"remaining_time":2.636196991},
{"learn":[0.1506101578],"iteration":695,"passed_time":6.016316384,"remaining_time":2.627816352},
{"learn":[0.1504505527],"iteration":696,"passed_time":6.024871023,"remaining_time":2.619133314},
{"learn":[0.150394863],"iteration":697,"passed_time":6.034086579,"remaining_time":2.6107366},
{"learn":[0.1502601533],"iteration":698,"passed_time":6.042922022,"remaining_time":2.602173861},
{"learn":[0.1501673228],"iteration":699,"passed_time":6.051575014,"remaining_time":2.593532149},
{"learn":[0.1500310585],"iteration":700,"passed_time":6.059885143,"remaining_time":2.584744162},
{"learn":[0.1499268345],"iteration":701,"passed_time":6.067488341,"remaining_time":2.575657444},
{"learn":[0.1498020489],"iteration":702,"passed_time":6.076145199,"remaining_time":2.567020091},
{"learn":[0.1496991985],"iteration":703,"passed_time":6.084466944,"remaining_time":2.558241783},
{"learn":[0.1495518388],"iteration":704,"passed_time":6.092280889,"remaining_time":2.549252287},
{"learn":[0.1494331653],"iteration":705,"passed_time":6.100681955,"remaining_time":2.540510616},
{"learn":[0.1493826931],"iteration":706,"passed_time":6.108815553,"remaining_time":2.531659062},
{"learn":[0.1491932945],"iteration":707,"passed_time":6.117428428,"remaining_time":2.523007205},
{"learn":[0.1490615451],"iteration":708,"passed_time":6.125157891,"remaining_time":2.513992872},
{"learn":[0.1489116086],"iteration":709,"passed_time":6.132921003,"remaining_time":2.504995903},
{"learn":[0.1487964702],"iteration":710,"passed_time":6.141100402,"remaining_time":2.496171612},
{"learn":[0.1486894351],"iteration":711,"passed_time":6.149071377,"remaining_time":2.487264827},
{"learn":[0.1486036962],"iteration":712,"passed_time":6.156733119,"remaining_time":2.478236192},
{"learn":[0.1484795176],"iteration":713,"passed_time":6.165138487,"remaining_time":2.469509254},
{"learn":[0.1483882204],"iteration":714,"passed_time":6.17311837,"remaining_time":2.460613616},
{"learn":[0.1483125973],"iteration":715,"passed_time":6.181236293,"remaining_time":2.451775289},
{"learn":[0.1482476649],"iteration":716,"passed_time":6.188882445,"remaining_time":2.442752764},
{"learn":[0.1481731598],"iteration":717,"passed_time":6.200995443,"remaining_time":2.435488461},
{"learn":[0.1480646233],"iteration":718,"passed_time":6.209713003,"remaining_time":2.426883663},
{"learn":[0.1479754984],"iteration":719,"passed_time":6.217975671,"remaining_time":2.41810165},
{"learn":[0.1478238049],"iteration":720,"passed_time":6.226647255,"remaining_time":2.409479312},
{"learn":[0.1477395675],"iteration":721,"passed_time":6.234856055,"remaining_time":2.400678647},
{"learn":[0.1476632735],"iteration":722,"passed_time":6.243421504,"remaining_time":2.392016261},
{"learn":[0.1475579953],"iteration":723,"passed_time":6.252145633,"remaining_time":2.383414634},
{"learn":[0.1474867486],"iteration":724,"passed_time":6.260385879,"remaining_time":2.374629126},
{"learn":[0.147382482],"iteration":725,"passed_time":6.268443523,"remaining_time":2.365776206},
{"learn":[0.1473052829],"iteration":726,"passed_time":6.276863846,"remaining_time":2.357061664},
{"learn":[0.147232226],"iteration":727,"passed_time":6.284433518,"remaining_time":2.348030106},
{"learn":[0.1471509594],"iteration":728,"passed_time":6.29307371,"remaining_time":2.339400515},
{"learn":[0.1470493974],"iteration":729,"passed_time":6.302385043,"remaining_time":2.331019126},
{"learn":[0.1469507743],"iteration":730,"passed_time":6.310588588,"remaining_time":2.322227538},
{"learn":[0.1468527688],"iteration":731,"passed_time":6.319502604,"remaining_time":2.313697675},
{"learn":[0.1467044615],"iteration":732,"passed_time":6.327646583,"remaining_time":2.304886272},
{"learn":[0.1466107898],"iteration":733,"passed_time":6.336567294,"remaining_time":2.296358175},
{"learn":[0.1465176079],"iteration":734,"passed_time":6.344288076,"remaining_time":2.287396381},
{"learn":[0.1463710149],"iteration":735,"passed_time":6.352860335,"remaining_time":2.278743381},
{"learn":[0.146293933],"iteration":736,"passed_time":6.36087031,"remaining_time":2.269889948},
{"learn":[0.1462055214],"iteration":737,"passed_time":6.37029163,"remaining_time":2.261539847},
{"learn":[0.1460956645],"iteration":738,"passed_time":6.378797142,"remaining_time":2.252863402},
{"learn":[0.1459437901],"iteration":739,"passed_time":6.386591358,"remaining_time":2.243937504},
{"learn":[0.1458471369],"iteration":740,"passed_time":6.395290816,"remaining_time":2.235331068},
{"learn":[0.1457322541],"iteration":741,"passed_time":6.402938164,"remaining_time":2.226358553},
{"learn":[0.1456563541],"iteration":742,"passed_time":6.4105579,"remaining_time":2.217380054},
{"learn":[0.1455734902],"iteration":743,"passed_time":6.418134232,"remaining_time":2.208390274},
{"learn":[0.1454670088],"iteration":744,"passed_time":6.426621415,"remaining_time":2.199716055},
{"learn":[0.1452832538],"iteration":745,"passed_time":6.434681251,"remaining_time":2.190896833},
{"learn":[0.145113352],"iteration":746,"passed_time":6.442636228,"remaining_time":2.182044131},
{"learn":[0.1449734461],"iteration":747,"passed_time":6.450376557,"remaining_time":2.173121514},
{"learn":[0.1448770378],"iteration":748,"passed_time":6.458920339,"remaining_time":2.164471302},
{"learn":[0.1447997536],"iteration":749,"passed_time":6.466906017,"remaining_time":2.155635339},
{"learn":[0.1447246842],"iteration":750,"passed_time":6.475027664,"remaining_time":2.146846722},
{"learn":[0.1446562698],"iteration":751,"passed_time":6.484077787,"remaining_time":2.138366079},
{"learn":[0.1445728842],"iteration":752,"passed_time":6.491943898,"remaining_time":2.129495542},
{"learn":[0.1444950889],"iteration":753,"passed_time":6.499355064,"remaining_time":2.120479239},
{"learn":[0.1444299755],"iteration":754,"passed_time":6.50748081,"remaining_time":2.111699071},
{"learn":[0.1442962668],"iteration":755,"passed_time":6.515600367,"remaining_time":2.102918637},
{"learn":[0.1441615465],"iteration":756,"passed_time":6.523209852,"remaining_time":2.093976214},
{"learn":[0.1440496984],"iteration":757,"passed_time":6.531439839,"remaining_time":2.08523541},
{"learn":[0.1439837864],"iteration":758,"passed_time":6.539131302,"remaining_time":2.076324959},
{"learn":[0.1438813938],"iteration":759,"passed_time":6.547672026,"remaining_time":2.067685903},
{"learn":[0.1438155031],"iteration":760,"passed_time":6.555952444,"remaining_time":2.058965354},
{"learn":[0.143678355],"iteration":761,"passed_time":6.563672941,"remaining_time":2.050071076},
{"learn":[0.143507857],"iteration":762,"passed_time":6.571512323,"remaining_time":2.041216803},
{"learn":[0.1434037394],"iteration":763,"passed_time":6.578745979,"remaining_time":2.032178077},
{"learn":[0.1433032529],"iteration":764,"passed_time":6.586632292,"remaining_time":2.02334456},
{"learn":[0.1432220502],"iteration":765,"passed_time":6.59462601,"remaining_time":2.014546327},
{"learn":[0.1431027697],"iteration":766,"passed_time":6.602706304,"remaining_time":2.005776491},
{"learn":[0.1429510869],"iteration":767,"passed_time":6.610765369,"remaining_time":1.997002039},
{"learn":[0.142778736],"iteration":768,"passed_time":6.618219392,"remaining_time":1.988047698},
{"learn":[0.1426438134],"iteration":769,"passed_time":6.626286376,"remaining_time":1.979280346},
{"learn":[0.1425489278],"iteration":770,"passed_time":6.634727827,"remaining_time":1.970626034},
{"learn":[0.1423995982],"iteration":771,"passed_time":6.643027649,"remaining_time":1.961930446},
{"learn":[0.1423264561],"iteration":772,"passed_time":6.650675652,"remaining_time":1.953044467},
{"learn":[0.1422349673],"iteration":773,"passed_time":6.669011928,"remaining_time":1.947282553},
{"learn":[0.1421525507],"iteration":774,"passed_time":6.676225565,"remaining_time":1.938259035},
{"learn":[0.1420691651],"iteration":775,"passed_time":6.684014693,"remaining_time":1.929406303},
{"learn":[0.1420016132],"iteration":776,"passed_time":6.692271398,"remaining_time":1.920690504},
{"learn":[0.1418898503],"iteration":777,"passed_time":6.700225708,"remaining_time":1.911889598},
{"learn":[0.141816868],"iteration":778,"passed_time":6.707848509,"remaining_time":1.902996817},
{"learn":[0.1416594565],"iteration":779,"passed_time":6.71616792,"remaining_time":1.894303772},
{"learn":[0.1415823532],"iteration":780,"passed_time":6.724239543,"remaining_time":1.885542202},
{"learn":[0.1415143542],"iteration":781,"passed_time":6.73251452,"remaining_time":1.876839086},
{"learn":[0.1413873006],"iteration":782,"passed_time":6.740765979,"remaining_time":1.868130546},
{"learn":[0.1412513025],"iteration":783,"passed_time":6.749163462,"remaining_time":1.859463403},
{"learn":[0.1411232373],"iteration":784,"passed_time":6.756998735,"remaining_time":1.850642966},
{"learn":[0.1410027429],"iteration":785,"passed_time":6.764842616,"remaining_time":1.841827379},
{"learn":[0.1408608564],"iteration":786,"passed_time":6.772653746,"remaining_time":1.833005398},
{"learn":[0.1407995444],"iteration":787,"passed_time":6.780858556,"remaining_time":1.824291896},
{"learn":[0.1407231652],"iteration":788,"passed_time":6.789313556,"remaining_time":1.815646591},
{"learn":[0.1406082079],"iteration":789,"passed_time":6.7970067,"remaining_time":1.806799249},
{"learn":[0.1405166232],"iteration":790,"passed_time":6.807322337,"remaining_time":1.798647748},
{"learn":[0.1404257945],"iteration":791,"passed_time":6.814710613,"remaining_time":1.789721979},
{"learn":[0.1403278742],"iteration":792,"passed_time":6.823020045,"remaining_time":1.781040541},
{"learn":[0.1402537418],"iteration":793,"passed_time":6.831168023,"remaining_time":1.772318152},
{"learn":[0.1401721451],"iteration":794,"passed_time":6.839189388,"remaining_time":1.763564559},
{"learn":[0.1400874178],"iteration":795,"passed_time":6.847935681,"remaining_time":1.754998592},
{"learn":[0.1399932137],"iteration":796,"passed_time":6.856292023,"remaining_time":1.746332849},
{"learn":[0.1398946013],"iteration":797,"passed_time":6.864547555,"remaining_time":1.737642364},
{"learn":[0.1397832643],"iteration":798,"passed_time":6.872209924,"remaining_time":1.728803748},
{"learn":[0.1396907106],"iteration":799,"passed_time":6.880182245,"remaining_time":1.720045561},
{"learn":[0.1395768607],"iteration":800,"passed_time":6.888633015,"remaining_time":1.711408202},
{"learn":[0.1395100649],"iteration":801,"passed_time":6.897938112,"remaining_time":1.702982227},
{"learn":[0.1394181395],"iteration":802,"passed_time":6.907510676,"remaining_time":1.69461968},
{"learn":[0.1393612677],"iteration":803,"passed_time":6.915770807,"remaining_time":1.685934177},
{"learn":[0.1392172303],"iteration":804,"passed_time":6.924157987,"remaining_time":1.677280506},
{"learn":[0.1391442905],"iteration":805,"passed_time":6.932263472,"remaining_time":1.668559694},
{"learn":[0.1390279702],"iteration":806,"passed_time":6.940830683,"remaining_time":1.659950833},
{"learn":[0.1389052184],"iteration":807,"passed_time":6.949477786,"remaining_time":1.651361058},
{"learn":[0.1387554736],"iteration":808,"passed_time":6.957233827,"remaining_time":1.642560768},
{"learn":[0.138634713],"iteration":809,"passed_time":6.965498292,"remaining_time":1.633882315},
{"learn":[0.1385604528],"iteration":810,"passed_time":6.974158105,"remaining_time":1.625297018},
{"learn":[0.1384571871],"iteration":811,"passed_time":6.98350205,"remaining_time":1.616869933},
{"learn":[0.1383719275],"iteration":812,"passed_time":6.992022492,"remaining_time":1.608251176},
{"learn":[0.1382571511],"iteration":813,"passed_time":7.000974316,"remaining_time":1.599731232},
{"learn":[0.1381841262],"iteration":814,"passed_time":7.009829064,"remaining_time":1.591188193},
{"learn":[0.1380696906],"iteration":815,"passed_time":7.019402059,"remaining_time":1.582806347},
{"learn":[0.1379718661],"iteration":816,"passed_time":7.027923803,"remaining_time":1.574186115},
{"learn":[0.1378729661],"iteration":817,"passed_time":7.035904451,"remaining_time":1.565445733},
{"learn":[0.1378283078],"iteration":818,"passed_time":7.044096796,"remaining_time":1.556753993},
{"learn":[0.1377651217],"iteration":819,"passed_time":7.053268769,"remaining_time":1.54827851},
{"learn":[0.1376381852],"iteration":820,"passed_time":7.062198172,"remaining_time":1.539748444},
{"learn":[0.1375390191],"iteration":821,"passed_time":7.070061276,"remaining_time":1.530986505},
{"learn":[0.1374831695],"iteration":822,"passed_time":7.077751018,"remaining_time":1.522189466},
{"learn":[0.1373421988],"iteration":823,"passed_time":7.085945311,"remaining_time":1.513502882},
{"learn":[0.137271346],"iteration":824,"passed_time":7.094657865,"remaining_time":1.504927426},
{"learn":[0.1371723183],"iteration":825,"passed_time":7.103382264,"remaining_time":1.496354133},
{"learn":[0.1370248202],"iteration":826,"passed_time":7.112308002,"remaining_time":1.487822593},
{"learn":[0.1369268147],"iteration":827,"passed_time":7.120710546,"remaining_time":1.479181418},
{"learn":[0.1368507018],"iteration":828,"passed_time":7.130513315,"remaining_time":1.470829646},
{"learn":[0.1367212417],"iteration":829,"passed_time":7.140208545,"remaining_time":1.462452353},
{"learn":[0.1366331602],"iteration":830,"passed_time":7.148177721,"remaining_time":1.45372086},
{"learn":[0.1365457709],"iteration":831,"passed_time":7.157697083,"remaining_time":1.445304219},
{"learn":[0.1364249464],"iteration":832,"passed_time":7.167084625,"remaining_time":1.436858502},
{"learn":[0.1363110326],"iteration":833,"passed_time":7.175698652,"remaining_time":1.428256566},
{"learn":[0.1362320873],"iteration":834,"passed_time":7.184912998,"remaining_time":1.419773227},
{"learn":[0.1361009341],"iteration":835,"passed_time":7.193302902,"remaining_time":1.411126407},
{"learn":[0.136026855],"iteration":836,"passed_time":7.202180393,"remaining_time":1.402575154},
{"learn":[0.1359729647],"iteration":837,"passed_time":7.210182215,"remaining_time":1.393853841},
{"learn":[0.1358723823],"iteration":838,"passed_time":7.21835183,"remaining_time":1.385166442},
{"learn":[0.1357987717],"iteration":839,"passed_time":7.226454172,"remaining_time":1.376467461},
{"learn":[0.1357138208],"iteration":840,"passed_time":7.235073332,"remaining_time":1.36786761},
{"learn":[0.1356624542],"iteration":841,"passed_time":7.242876516,"remaining_time":1.359114596},
{"learn":[0.1355205677],"iteration":842,"passed_time":7.251859348,"remaining_time":1.350583532},
{"learn":[0.1354385238],"iteration":843,"passed_time":7.26066506,"remaining_time":1.34201866},
{"learn":[0.1353311479],"iteration":844,"passed_time":7.269695257,"remaining_time":1.333494396},
{"learn":[0.1352178729],"iteration":845,"passed_time":7.278981543,"remaining_time":1.325015553},
{"learn":[0.1351055457],"iteration":846,"passed_time":7.287202681,"remaining_time":1.316342397},
{"learn":[0.1350248008],"iteration":847,"passed_time":7.296170749,"remaining_time":1.307804191},
{"learn":[0.1349560138],"iteration":848,"passed_time":7.305744931,"remaining_time":1.299372773},
{"learn":[0.1349048175],"iteration":849,"passed_time":7.314123712,"remaining_time":1.290727714},
{"learn":[0.1348627041],"iteration":850,"passed_time":7.322919664,"remaining_time":1.282156322},
{"learn":[0.1347879648],"iteration":851,"passed_time":7.331701791,"remaining_time":1.273582001},
{"learn":[0.1346764362],"iteration":852,"passed_time":7.34057932,"remaining_time":1.265023634},
{"learn":[0.1346157417],"iteration":853,"passed_time":7.348856781,"remaining_time":1.256361932},
{"learn":[0.1345304714],"iteration":854,"passed_time":7.357050693,"remaining_time":1.24768696},
{"learn":[0.1344641761],"iteration":855,"passed_time":7.364995474,"remaining_time":1.238971201},
{"learn":[0.1342918678],"iteration":856,"passed_time":7.37321708,"remaining_time":1.230303433},
{"learn":[0.134225253],"iteration":857,"passed_time":7.381290181,"remaining_time":1.221612128},
{"learn":[0.1340808749],"iteration":858,"passed_time":7.389434631,"remaining_time":1.212933973},
{"learn":[0.1339589856],"iteration":859,"passed_time":7.398300324,"remaining_time":1.204374471},
{"learn":[0.133893755],"iteration":860,"passed_time":7.406528308,"remaining_time":1.195711306},
{"learn":[0.1337842495],"iteration":861,"passed_time":7.414497022,"remaining_time":1.187007644},
{"learn":[0.1336630524],"iteration":862,"passed_time":7.422500342,"remaining_time":1.178311178},
{"learn":[0.1335778566],"iteration":863,"passed_time":7.430447413,"remaining_time":1.169607463},
{"learn":[0.1335021802],"iteration":864,"passed_time":7.439104391,"remaining_time":1.161016292},
{"learn":[0.1334202002],"iteration":865,"passed_time":7.44766282,"remaining_time":1.15240972},
{"learn":[0.133315465],"iteration":866,"passed_time":7.456730567,"remaining_time":1.14388139},
{"learn":[0.1332026267],"iteration":867,"passed_time":7.467098532,"remaining_time":1.135549546},
{"learn":[0.133124629],"iteration":868,"passed_time":7.476023033,"remaining_time":1.126995417},
{"learn":[0.1330546175],"iteration":869,"passed_time":7.484194006,"remaining_time":1.11832784},
{"learn":[0.1329806981],"iteration":870,"passed_time":7.493045787,"remaining_time":1.109762235},
{"learn":[0.1328629509],"iteration":871,"passed_time":7.502248725,"remaining_time":1.101247519},
{"learn":[0.1327327348],"iteration":872,"passed_time":7.510853099,"remaining_time":1.092644151},
{"learn":[0.1326542686],"iteration":873,"passed_time":7.518570644,"remaining_time":1.08391293},
{"learn":[0.1325679547],"iteration":874,"passed_time":7.527464539,"remaining_time":1.075352077},
{"learn":[0.1324458844],"iteration":875,"passed_time":7.535374968,"remaining_time":1.066651251},
{"learn":[0.1323851474],"iteration":876,"passed_time":7.543322443,"remaining_time":1.057957424},
{"learn":[0.1322989294],"iteration":877,"passed_time":7.551023736,"remaining_time":1.049231089},
{"learn":[0.1322664739],"iteration":878,"passed_time":7.558557492,"remaining_time":1.040484023},
{"learn":[0.1321809267],"iteration":879,"passed_time":7.566898951,"remaining_time":1.031849857},
{"learn":[0.1320311286],"iteration":880,"passed_time":7.576957076,"remaining_time":1.023448232},
{"learn":[0.1319166717],"iteration":881,"passed_time":7.58499901,"remaining_time":1.01477311},
{"learn":[0.1318447968],"iteration":882,"passed_time":7.593190901,"remaining_time":1.006119293},
{"learn":[0.1317226732],"iteration":883,"passed_time":7.601047186,"remaining_time":0.9974224814},
{"learn":[0.1316844783],"iteration":884,"passed_time":7.609892597,"remaining_time":0.9888561002},
{"learn":[0.1316032756],"iteration":885,"passed_time":7.618661671,"remaining_time":0.9802792669},
{"learn":[0.1315095613],"iteration":886,"passed_time":7.628221107,"remaining_time":0.971802689},
{"learn":[0.1314375479],"iteration":887,"passed_time":7.63691127,"remaining_time":0.963214034},
{"learn":[0.1312601818],"iteration":888,"passed_time":7.644941247,"remaining_time":0.9545427204},
{"learn":[0.1311675429],"iteration":889,"passed_time":7.653453478,"remaining_time":0.9459324524},
{"learn":[0.1310935703],"iteration":890,"passed_time":7.661312609,"remaining_time":0.9372425077},
{"learn":[0.1309587115],"iteration":891,"passed_time":7.670662477,"remaining_time":0.9287349188},
{"learn":[0.1308646139],"iteration":892,"passed_time":7.678957921,"remaining_time":0.9200991014},
{"learn":[0.1307465047],"iteration":893,"passed_time":7.686750977,"remaining_time":0.9114044783},
{"learn":[0.1306009978],"iteration":894,"passed_time":7.694692033,"remaining_time":0.9027292329},
{"learn":[0.1305510793],"iteration":895,"passed_time":7.702499426,"remaining_time":0.8940401119},
{"learn":[0.1304710053],"iteration":896,"passed_time":7.711521913,"remaining_time":0.8854924828},
{"learn":[0.1303914317],"iteration":897,"passed_time":7.719573262,"remaining_time":0.8768334886},
{"learn":[0.1303323452],"iteration":898,"passed_time":7.727913161,"remaining_time":0.8682082639},
{"learn":[0.1302785294],"iteration":899,"passed_time":7.736742317,"remaining_time":0.8596380353},
{"learn":[0.1301756364],"iteration":900,"passed_time":7.745111472,"remaining_time":0.8510166878},
{"learn":[0.130096936],"iteration":901,"passed_time":7.75322511,"remaining_time":0.8423681383},
{"learn":[0.130027393],"iteration":902,"passed_time":7.762344731,"remaining_time":0.833828836},
{"learn":[0.129946531],"iteration":903,"passed_time":7.77154706,"remaining_time":0.825297033},
{"learn":[0.1298659671],"iteration":904,"passed_time":7.780519525,"remaining_time":0.8167396186},
{"learn":[0.1297824431],"iteration":905,"passed_time":7.789530509,"remaining_time":0.8081852846},
{"learn":[0.1296985783],"iteration":906,"passed_time":7.797809574,"remaining_time":0.7995548957},
{"learn":[0.1296211131],"iteration":907,"passed_time":7.807020317,"remaining_time":0.7910196797},
{"learn":[0.1295521131],"iteration":908,"passed_time":7.814975942,"remaining_time":0.7823573276},
{"learn":[0.129506571],"iteration":909,"passed_time":7.823698061,"remaining_time":0.7737723357},
{"learn":[0.1293904424],"iteration":910,"passed_time":7.831875228,"remaining_time":0.7651338038},
{"learn":[0.1293345822],"iteration":911,"passed_time":7.840386907,"remaining_time":0.7565285612},
{"learn":[0.1292241397],"iteration":912,"passed_time":7.848678399,"remaining_time":0.7479025418},
{"learn":[0.1291565985],"iteration":913,"passed_time":7.857950147,"remaining_time":0.7393694887},
{"learn":[0.1290806985],"iteration":914,"passed_time":7.867115535,"remaining_time":0.7308249404},
{"learn":[0.1289898166],"iteration":915,"passed_time":7.875593305,"remaining_time":0.72221598},
{"learn":[0.1288610167],"iteration":916,"passed_time":7.883859507,"remaining_time":0.713588156},
{"learn":[0.1287813047],"iteration":917,"passed_time":7.892790297,"remaining_time":0.705020484},
{"learn":[0.1287329195],"iteration":918,"passed_time":7.900914804,"remaining_time":0.6963809566},
{"learn":[0.1286896029],"iteration":919,"passed_time":7.908857967,"remaining_time":0.6877267798},
{"learn":[0.1285634543],"iteration":920,"passed_time":7.917538869,"remaining_time":0.6791374274},
{"learn":[0.1284522558],"iteration":921,"passed_time":7.926230524,"remaining_time":0.6705487862},
{"learn":[0.1282712799],"iteration":922,"passed_time":7.934446382,"remaining_time":0.6619202291},
{"learn":[0.1282180818],"iteration":923,"passed_time":7.942691757,"remaining_time":0.653294993},
{"learn":[0.1281728911],"iteration":924,"passed_time":7.951117798,"remaining_time":0.6446852269},
{"learn":[0.1280762059],"iteration":925,"passed_time":7.959336529,"remaining_time":0.6360592907},
{"learn":[0.1280162569],"iteration":926,"passed_time":7.968116438,"remaining_time":0.627478425},
{"learn":[0.1279659977],"iteration":927,"passed_time":7.976833134,"remaining_time":0.6188922259},
{"learn":[0.1278574824],"iteration":928,"passed_time":7.985644084,"remaining_time":0.6103129494},
{"learn":[0.1277476255],"iteration":929,"passed_time":7.993892704,"remaining_time":0.6016908487},
{"learn":[0.1276234043],"iteration":930,"passed_time":8.001905202,"remaining_time":0.5930520504},
{"learn":[0.1274860007],"iteration":931,"passed_time":8.010042452,"remaining_time":0.5844236982},
{"learn":[0.1273466697],"iteration":932,"passed_time":8.018230749,"remaining_time":0.5758000645},
{"learn":[0.1271735522],"iteration":933,"passed_time":8.027637215,"remaining_time":0.5672634435},
{"learn":[0.1270338699],"iteration":934,"passed_time":8.03669804,"remaining_time":0.5587009332},
{"learn":[0.1269312111],"iteration":935,"passed_time":8.046281665,"remaining_time":0.5501731053},
{"learn":[0.1268112704],"iteration":936,"passed_time":8.055843006,"remaining_time":0.5416415255},
{"learn":[0.1267577316],"iteration":937,"passed_time":8.064618863,"remaining_time":0.533055831},
{"learn":[0.1267095168],"iteration":938,"passed_time":8.072492171,"remaining_time":0.5244110995},
{"learn":[0.126598084],"iteration":939,"passed_time":8.082149885,"remaining_time":0.5158819076},
{"learn":[0.1265234831],"iteration":940,"passed_time":8.090039299,"remaining_time":0.507239446},
{"learn":[0.1264182794],"iteration":941,"passed_time":8.098072077,"remaining_time":0.4986074103},
{"learn":[0.1263401327],"iteration":942,"passed_time":8.106249152,"remaining_time":0.4899853676},
{"learn":[0.1262563105],"iteration":943,"passed_time":8.114240857,"remaining_time":0.4813532712},
{"learn":[0.1261410124],"iteration":944,"passed_time":8.122231902,"remaining_time":0.4727224917},
{"learn":[0.1260217745],"iteration":945,"passed_time":8.130486819,"remaining_time":0.4641081271},
{"learn":[0.1259510389],"iteration":946,"passed_time":8.138262086,"remaining_time":0.4554676774},
{"learn":[0.1258457288],"iteration":947,"passed_time":8.146258237,"remaining_time":0.4468411691},
{"learn":[0.1257671242],"iteration":948,"passed_time":8.154800996,"remaining_time":0.4382453644},
{"learn":[0.1256300719],"iteration":949,"passed_time":8.164388067,"remaining_time":0.4297046351},
{"learn":[0.1255251238],"iteration":950,"passed_time":8.176297163,"remaining_time":0.421281347},
{"learn":[0.1254631623],"iteration":951,"passed_time":8.184289438,"remaining_time":0.412653249},
{"learn":[0.1253926396],"iteration":952,"passed_time":8.192453499,"remaining_time":0.4040349574},
{"learn":[0.1253357147],"iteration":953,"passed_time":8.200575465,"remaining_time":0.3954155884},
{"learn":[0.1252274443],"iteration":954,"passed_time":8.209322614,"remaining_time":0.38682672},
{"learn":[0.125149862],"iteration":955,"passed_time":8.217117135,"remaining_time":0.3781936757},
{"learn":[0.1250397602],"iteration":956,"passed_time":8.225633154,"remaining_time":0.3695948021},
{"learn":[0.1249784375],"iteration":957,"passed_time":8.234296053,"remaining_time":0.361002541},
{"learn":[0.1248533538],"iteration":958,"passed_time":8.242421304,"remaining_time":0.3523871465},
{"learn":[0.1247651659],"iteration":959,"passed_time":8.250301093,"remaining_time":0.3437625455},
{"learn":[0.1246883289],"iteration":960,"passed_time":8.259005082,"remaining_time":0.335172943},
{"learn":[0.1246164113],"iteration":961,"passed_time":8.267077396,"remaining_time":0.3265581508},
{"learn":[0.1245199817],"iteration":962,"passed_time":8.274906734,"remaining_time":0.3179351497},
{"learn":[0.1244408767],"iteration":963,"passed_time":8.283165784,"remaining_time":0.3093298426},
{"learn":[0.1243376003],"iteration":964,"passed_time":8.291683708,"remaining_time":0.3007346423},
{"learn":[0.1242561633],"iteration":965,"passed_time":8.300351514,"remaining_time":0.2921448773},
{"learn":[0.1241687634],"iteration":966,"passed_time":8.309440602,"remaining_time":0.2835693277},
{"learn":[0.1240863254],"iteration":967,"passed_time":8.317996096,"remaining_time":0.2749750775},
{"learn":[0.1239910033],"iteration":968,"passed_time":8.32689909,"remaining_time":0.2663920245},
{"learn":[0.1238937431],"iteration":969,"passed_time":8.335414792,"remaining_time":0.2577963338},
{"learn":[0.1238146807],"iteration":970,"passed_time":8.342884861,"remaining_time":0.2491695788},
{"learn":[0.1237414214],"iteration":971,"passed_time":8.350974808,"remaining_time":0.2405630603},
{"learn":[0.1236260701],"iteration":972,"passed_time":8.360332153,"remaining_time":0.231992773},
{"learn":[0.1235213776],"iteration":973,"passed_time":8.368938793,"remaining_time":0.2234008302},
{"learn":[0.1234270031],"iteration":974,"passed_time":8.376915626,"remaining_time":0.2147927084},
{"learn":[0.1233595577],"iteration":975,"passed_time":8.385444261,"remaining_time":0.206199449},
{"learn":[0.1232878851],"iteration":976,"passed_time":8.393729113,"remaining_time":0.197600583},
{"learn":[0.123215499],"iteration":977,"passed_time":8.401572356,"remaining_time":0.1889924252},
{"learn":[0.1231491398],"iteration":978,"passed_time":8.409467868,"remaining_time":0.1803869512},
{"learn":[0.1230713231],"iteration":979,"passed_time":8.418468936,"remaining_time":0.1718054885},
{"learn":[0.1229859676],"iteration":980,"passed_time":8.426932335,"remaining_time":0.1632127567},
{"learn":[0.1228952241],"iteration":981,"passed_time":8.435607722,"remaining_time":0.1546241741},
{"learn":[0.1227868686],"iteration":982,"passed_time":8.444534996,"remaining_time":0.146039771},
{"learn":[0.1227482904],"iteration":983,"passed_time":8.452566996,"remaining_time":0.1374401138},
{"learn":[0.1226617104],"iteration":984,"passed_time":8.46147932,"remaining_time":0.128855015},
{"learn":[0.1225561873],"iteration":985,"passed_time":8.470407546,"remaining_time":0.1202694783},
{"learn":[0.1224783068],"iteration":986,"passed_time":8.479174229,"remaining_time":0.1116811195},
{"learn":[0.1223502522],"iteration":987,"passed_time":8.48858723,"remaining_time":0.1031002498},
{"learn":[0.1222917726],"iteration":988,"passed_time":8.498872723,"remaining_time":0.09452740137},
{"learn":[0.1221882833],"iteration":989,"passed_time":8.510116878,"remaining_time":0.08596077654},
{"learn":[0.1220696523],"iteration":990,"passed_time":8.523799882,"remaining_time":0.07741089701},
{"learn":[0.1219949236],"iteration":991,"passed_time":8.533416473,"remaining_time":0.06881787479},
{"learn":[0.1219067996],"iteration":992,"passed_time":8.542483732,"remaining_time":0.06021891856},
{"learn":[0.1218130853],"iteration":993,"passed_time":8.55352908,"remaining_time":0.05163096024},
{"learn":[0.121768789],"iteration":994,"passed_time":8.563518012,"remaining_time":0.04303275383},
{"learn":[0.1216974145],"iteration":995,"passed_time":8.573252592,"remaining_time":0.0344307333},
{"learn":[0.1215636739],"iteration":996,"passed_time":8.582983226,"remaining_time":0.02582642896},
{"learn":[0.1215309202],"iteration":997,"passed_time":8.591964002,"remaining_time":0.01721836473},
{"learn":[0.1214386966],"iteration":998,"passed_time":8.601237654,"remaining_time":0.008609847501},
{"learn":[0.121378673],"iteration":999,"passed_time":8.609651081,"remaining_time":0}
]}